{
  "type": "Feature",
  "properties": {
    "gn:admin1_code":"12",
    "gn:asciiname":"Mahawish",
    "gn:country_code":"JO",
    "gn:dem":1191,
    "gn:feature_class":"P",
    "gn:feature_code":"PPL",
    "gn:name":"Mah\u0101wish",
    "gn:population":0,
    "gn:timezone":"Asia/Amman",
    "iso:country":"JO",
    "name:ara_x_preferred":[
        "\u0645\u0647\u0627\u0648\u0634"
    ],
    "name:und_x_variant":[
        "Mah\u0101wish"
    ],
    "wof:name":"Mahawish",
    "wof:placetype":"locality"
},
  "geometry": {"coordinates":[35.65453,30.86336],"type":"Point"}
}