{
  "type": "Feature",
  "properties": {
    "gn:admin1_code":"15",
    "gn:asciiname":"Al Husayniyah",
    "gn:country_code":"JO",
    "gn:dem":973,
    "gn:feature_class":"P",
    "gn:feature_code":"PPL",
    "gn:name":"Al \u1e28usayn\u012byah",
    "gn:population":0,
    "gn:timezone":"Asia/Amman",
    "iso:country":"JO",
    "name:ara_x_preferred":[
        "\u0627\u0644\u062d\u0633\u064a\u0646\u064a\u0629"
    ],
    "name:und_x_variant":[
        "El \u1e24useiniya",
        "Al \u1e28usayn\u012byah"
    ],
    "wof:name":"Al Husayniyah",
    "wof:placetype":"locality"
},
  "geometry": {"coordinates":[36.60745,32.34684],"type":"Point"}
}