{
  "type": "Feature",
  "properties": {
    "gn:admin1_code":"23",
    "gn:asciiname":"Al Faysaliyah",
    "gn:country_code":"JO",
    "gn:dem":811,
    "gn:feature_class":"P",
    "gn:feature_code":"PPLA3",
    "gn:name":"Al Fay\u015fal\u012byah",
    "gn:population":0,
    "gn:timezone":"Asia/Amman",
    "iso:country":"JO",
    "name:ara_x_preferred":[
        "\u0627\u0644\u0641\u064a\u0635\u0644\u064a\u0629"
    ],
    "name:und_x_variant":[
        "Kefeir el Wekhyan",
        "Kufeir el Wakhy\u0101n",
        "Kufayr al Wakhy\u0101n",
        "Al Fay\u015fal\u012byah"
    ],
    "wof:name":"Al Faysaliyah",
    "wof:placetype":"locality"
},
  "geometry": {"coordinates":[35.76922000000001,31.74909],"type":"Point"}
}