{
  "type": "Feature",
  "properties": {
    "gn:admin1_code":"18",
    "gn:asciiname":"As Sawwan",
    "gn:country_code":"JO",
    "gn:dem":399,
    "gn:feature_class":"P",
    "gn:feature_code":"PPL",
    "gn:name":"A\u015f \u015eaww\u0101n",
    "gn:population":0,
    "gn:timezone":"Asia/Amman",
    "iso:country":"JO",
    "name:ara_x_preferred":[
        "\u0627\u0644\u0635\u0648\u0627\u0646"
    ],
    "name:und_x_variant":[
        "Es \u1e62uww\u0101n",
        "Suwwan",
        "Es Sowan",
        "Khirbat a\u015f \u015eaww\u0101n",
        "A\u015f \u015eaww\u0101n"
    ],
    "wof:name":"As Sawwan",
    "wof:placetype":"locality"
},
  "geometry": {"coordinates":[35.71004,32.49268],"type":"Point"}
}