{
  "type": "Feature",
  "properties": {
    "gn:admin1_code":"18",
    "gn:asciiname":"Tuqbul",
    "gn:country_code":"JO",
    "gn:dem":428,
    "gn:feature_class":"P",
    "gn:feature_code":"PPL",
    "gn:name":"Tuqbul",
    "gn:population":0,
    "gn:timezone":"Asia/Amman",
    "iso:country":"JO",
    "name:ara_x_preferred":[
        "\u062a\u0642\u0628\u0644"
    ],
    "name:und_x_variant":[
        "Tuqbut",
        "Tuqbul"
    ],
    "wof:name":"Tuqbul",
    "wof:placetype":"locality"
},
  "geometry": {"coordinates":[35.80859,32.60225],"type":"Point"}
}