{
  "type": "Feature",
  "properties": {
    "gn:admin1_code":"16",
    "gn:asciiname":"Al Qunaytirah",
    "gn:cc2":"JO",
    "gn:country_code":"JO",
    "gn:dem":733,
    "gn:feature_class":"P",
    "gn:feature_code":"PPL",
    "gn:name":"Al Qunay\u0163irah",
    "gn:population":0,
    "gn:timezone":"Asia/Amman",
    "iso:country":"JO",
    "name:sco_x_preferred":[
        "Al Qunaytirah"
    ],
    "name:und_x_variant":[
        "Al Qunay\u0163ira",
        "Al Qunay\u0163irah"
    ],
    "wof:name":"Al Qunaytirah",
    "wof:placetype":"locality"
},
  "geometry": {"coordinates":[36.03889,31.60556],"type":"Point"}
}