{
  "type": "Feature",
  "properties": {
    "gn:admin1_code":"12",
    "gn:asciiname":"Butaynah",
    "gn:country_code":"JO",
    "gn:dem":1206,
    "gn:feature_class":"P",
    "gn:feature_code":"PPL",
    "gn:name":"Bu\u0163aynah",
    "gn:population":0,
    "gn:timezone":"Asia/Amman",
    "iso:country":"JO",
    "name:ara_x_preferred":[
        "\u0628\u0637\u064a\u0646\u0629"
    ],
    "name:und_x_variant":[
        "Bu\u1e6deina",
        "Khirbat Buteina",
        "Bu\u0163aynah",
        "Khirbat Bu\u0163aynah"
    ],
    "wof:name":"Butaynah",
    "wof:placetype":"locality"
},
  "geometry": {"coordinates":[35.63399000000001,30.86103],"type":"Point"}
}