{
  "type": "Feature",
  "properties": {
    "gn:admin1_code":"18",
    "gn:asciiname":"Al Madarij",
    "gn:country_code":"JO",
    "gn:dem":-220,
    "gn:feature_class":"P",
    "gn:feature_code":"PPL",
    "gn:name":"Al Mad\u0101rij",
    "gn:population":0,
    "gn:timezone":"Asia/Amman",
    "iso:country":"JO",
    "name:ara_x_preferred":[
        "\u0627\u0644\u0645\u062f\u0627\u0631\u062c"
    ],
    "name:und_x_variant":[
        "Al Mad\u0101rij"
    ],
    "wof:name":"Al Madarij",
    "wof:placetype":"locality"
},
  "geometry": {"coordinates":[35.59455999999999,32.45661],"type":"Point"}
}