{
  "type": "Feature",
  "properties": {
    "iso:country":"JO",
    "name:ara_x_preferred":[
        "\u0645\u0624\u062a\u0629"
    ],
    "name:cat_x_preferred":[
        "Muta"
    ],
    "name:eng_x_preferred":[
        "Mu'tah"
    ],
    "name:fas_x_preferred":[
        "\u0645\u0648\u062a\u0647"
    ],
    "name:fra_x_preferred":[
        "Mu'tah"
    ],
    "name:hin_x_preferred":[
        "\u092e\u0941\u0924\u094d\u0939\u093e"
    ],
    "name:ind_x_preferred":[
        "Mu'tah"
    ],
    "name:nld_x_preferred":[
        "Mu'tah"
    ],
    "name:nno_x_preferred":[
        "Mu'tah"
    ],
    "name:pol_x_preferred":[
        "Muta"
    ],
    "name:rus_x_preferred":[
        "\u041c\u0443\u0442\u0430"
    ],
    "name:sco_x_preferred":[
        "Mu'tah"
    ],
    "name:sqi_x_preferred":[
        "Mu'tah"
    ],
    "name:swe_x_preferred":[
        "Mu'tah"
    ],
    "name:und_x_variant":[
        "Mauta"
    ],
    "name:urd_x_preferred":[
        "\u0645\u0648\u062a\u06c1"
    ],
    "qs:gn_country":"JO",
    "qs:gn_fcode":"PPL",
    "qs:gn_pop":0,
    "qs:name":"Mu'tah",
    "qs:name_adm0":"\u0627\u0644\u0623\u0631\u062f\u0646",
    "qs:name_adm1":"\u0627\u0644\u0643\u0631\u0643",
    "qs:photos":42,
    "qs:photos_1k":9,
    "qs:photos_9k":1,
    "qs:photos_9r":2,
    "qs:photos_all":42,
    "qs:photos_sr":2,
    "qs:placetype":"Town",
    "qs:pop_sr":"0",
    "qs:woe_adm0":23424860,
    "wd:wordcount":58,
    "wof:name":"Mu'tah",
    "wof:placetype":"locality"
},
  "geometry": {"coordinates":[35.69444,31.0925],"type":"Point"}
}