{
  "type": "Feature",
  "properties": {
    "gn:admin1_code":"15",
    "gn:asciiname":"Al Matallah",
    "gn:country_code":"JO",
    "gn:dem":631,
    "gn:feature_class":"P",
    "gn:feature_code":"PPL",
    "gn:name":"Al Ma\u0163allah",
    "gn:population":0,
    "gn:timezone":"Asia/Amman",
    "iso:country":"JO",
    "name:ara_x_preferred":[
        "\u0627\u0644\u0645\u0637\u0644\u0629"
    ],
    "name:und_x_variant":[
        "Al Ma\u0163allah"
    ],
    "wof:name":"Al Matallah",
    "wof:placetype":"locality"
},
  "geometry": {"coordinates":[36.18996,32.43396],"type":"Point"}
}