{
  "type": "Feature",
  "properties": {
    "gn:admin1_code":"16",
    "gn:asciiname":"Al Falij",
    "gn:country_code":"JO",
    "gn:dem":875,
    "gn:feature_class":"P",
    "gn:feature_code":"PPL",
    "gn:name":"Al F\u0101lij",
    "gn:population":0,
    "gn:timezone":"Asia/Amman",
    "iso:country":"JO",
    "name:ara_x_preferred":[
        "Al F\u0101lij"
    ],
    "name:ara_x_variant":[
        "\u0627\u0644\u0641\u0627\u0644\u062c"
    ],
    "wof:name":"Al Falij",
    "wof:placetype":"locality"
},
  "geometry": {"coordinates":[36.20682,31.67252],"type":"Point"}
}