{
  "type": "Feature",
  "properties": {
    "gn:admin1_code":"18",
    "gn:asciiname":"Al Mashari`",
    "gn:country_code":"JO",
    "gn:dem":-192,
    "gn:feature_class":"P",
    "gn:feature_code":"PPL",
    "gn:name":"Al Mash\u0101ri\u2018",
    "gn:population":0,
    "gn:timezone":"Asia/Amman",
    "iso:country":"JO",
    "name:ara_x_preferred":[
        "\u0627\u0644\u0645\u0634\u0627\u0631\u0639"
    ],
    "name:und_x_variant":[
        "Ash Shaykh Muhammad",
        "Khirbat esh Sheikh Muhammad",
        "Khirbat ash Shaykh Mu\u1e29ammad",
        "Al Mash\u0101ri\u2018"
    ],
    "wof:name":"Al Mashari`",
    "wof:placetype":"locality"
},
  "geometry": {"coordinates":[35.59442,32.43432],"type":"Point"}
}