{
  "type": "Feature",
  "properties": {
    "gn:admin1_code":"19",
    "gn:asciiname":"Ar Rusays",
    "gn:country_code":"JO",
    "gn:dem":1470,
    "gn:feature_class":"P",
    "gn:feature_code":"PPL",
    "gn:name":"Ar Rusays",
    "gn:population":0,
    "gn:timezone":"Asia/Amman",
    "iso:country":"JO",
    "name:ara_x_preferred":[
        "\u0627\u0644\u0631\u0633\u064a\u0633"
    ],
    "name:und_x_variant":[
        "Er Ruseis",
        "Ar Ras\u012bs",
        "Ar Rusays"
    ],
    "wof:name":"Ar Rusays",
    "wof:placetype":"locality"
},
  "geometry": {"coordinates":[35.41614,30.13902],"type":"Point"}
}