{
  "type": "Feature",
  "properties": {
    "gn:admin1_code":"15",
    "gn:asciiname":"Hayyan ar Ruwaybid",
    "gn:country_code":"JO",
    "gn:dem":660,
    "gn:feature_class":"P",
    "gn:feature_code":"PPL",
    "gn:name":"\u1e28ayy\u0101n ar Ruwaybi\u1e11",
    "gn:population":0,
    "gn:timezone":"Asia/Amman",
    "iso:country":"JO",
    "name:ara_x_preferred":[
        "\u062d\u064a\u0627\u0646 \u0627\u0644\u0631\u0648\u064a\u0628\u0636"
    ],
    "name:ara_x_variant":[
        "\u062d\u064a\u0627\u0646 \u0627\u0644\u0631\u0648\u064a\u0628\u0636 \u0627\u0644\u0634\u0631\u0642\u064a",
        "\u062d\u064a\u0627\u0646 \u0627\u0644\u0631\u0648\u064a\u0628\u0636 \u0627\u0644\u063a\u0631\u0628\u064a"
    ],
    "name:und_x_variant":[
        "Haiy\u0101n er Ruweibid esh Sharqi",
        "\u1e28ayy\u0101n ar Ruwaybi\u1e11 ash Sharq\u012b",
        "\u1e28ayy\u0101n ar Ruwaybi\u1e11",
        "\u1e28ayy\u0101n ar Ruwaybi\u1e11 al Gharb\u012b"
    ],
    "wof:name":"Hayyan ar Ruwaybid",
    "wof:placetype":"locality"
},
  "geometry": {"coordinates":[36.12931,32.24447],"type":"Point"}
}