{
  "type": "Feature",
  "properties": {
    "gn:admin1_code":"09",
    "gn:asciiname":"Al Ifranj",
    "gn:cc2":"JO",
    "gn:country_code":"JO",
    "gn:dem":906,
    "gn:feature_class":"P",
    "gn:feature_code":"PPL",
    "gn:name":"Al Ifranj",
    "gn:population":0,
    "gn:timezone":"Asia/Amman",
    "iso:country":"JO",
    "name:und_x_variant":[
        "Ifranj",
        "El Efranj",
        "El Ifran",
        "El Ifranj",
        "Al Ifranj"
    ],
    "wof:name":"Al Ifranj",
    "wof:placetype":"locality"
},
  "geometry": {"coordinates":[35.6875,31.17278],"type":"Point"}
}