{
  "type": "Feature",
  "properties": {
    "gn:admin1_code":"23",
    "gn:asciiname":"Al Yusra al Jadidah",
    "gn:country_code":"JO",
    "gn:dem":829,
    "gn:feature_class":"P",
    "gn:feature_code":"PPL",
    "gn:name":"Al Yusr\u00e1 al Jad\u012bdah",
    "gn:population":0,
    "gn:timezone":"Asia/Amman",
    "iso:country":"JO",
    "name:ara_x_preferred":[
        "\u0627\u0644\u064a\u0633\u0631\u0649 \u0627\u0644\u062c\u062f\u064a\u062f\u0629"
    ],
    "name:und_x_variant":[
        "Al Yusr\u00e1 al Jad\u012bdah"
    ],
    "wof:name":"Al Yusra al Jadidah",
    "wof:placetype":"locality"
},
  "geometry": {"coordinates":[35.76156,31.73788],"type":"Point"}
}