{
  "type": "Feature",
  "properties": {
    "gn:admin1_code":"02",
    "gn:asciiname":"Buyudah ash Sharqiyah",
    "gn:country_code":"JO",
    "gn:dem":485,
    "gn:feature_class":"P",
    "gn:feature_code":"PPL",
    "gn:name":"Buy\u016b\u1e11ah ash Sharq\u012byah",
    "gn:population":0,
    "gn:timezone":"Asia/Amman",
    "iso:country":"JO",
    "name:ara_x_preferred":[
        "\u0628\u064a\u0648\u0636\u0629 \u0627\u0644\u0634\u0631\u0642\u064a\u0629"
    ],
    "name:und_x_variant":[
        "Buy\u016b\u1e11ah ash Sharq\u012byah"
    ],
    "wof:name":"Buyudah ash Sharqiyah",
    "wof:placetype":"locality"
},
  "geometry": {"coordinates":[35.7313,32.13124000000001],"type":"Point"}
}