{
  "type": "Feature",
  "properties": {
    "gn:admin1_code":"15",
    "gn:asciiname":"Umm Suwaywiniyah",
    "gn:country_code":"JO",
    "gn:dem":618,
    "gn:feature_class":"P",
    "gn:feature_code":"PPLL",
    "gn:name":"Umm \u015euwaywin\u012byah",
    "gn:population":0,
    "gn:timezone":"Asia/Amman",
    "iso:country":"JO",
    "name:ara_x_preferred":[
        "\u0623\u0645 \u0635\u0648\u064a\u0648\u0646\u064a\u0629"
    ],
    "name:und_x_variant":[
        "Umm \u015euwaywin\u012byah",
        "Umm \u015euwayw\u012bnah"
    ],
    "wof:name":"Umm Suwaywiniyah",
    "wof:placetype":"locality"
},
  "geometry": {"coordinates":[36.0348,32.21073],"type":"Point"}
}