{
  "type": "Feature",
  "properties": {
    "gn:admin1_code":"17",
    "gn:asciiname":"`Awjan al Gharbi",
    "gn:country_code":"JO",
    "gn:dem":637,
    "gn:feature_class":"P",
    "gn:feature_code":"PPL",
    "gn:name":"\u2018Awj\u0101n al Gharb\u012b",
    "gn:population":0,
    "gn:timezone":"Asia/Amman",
    "iso:country":"JO",
    "name:und_x_variant":[
        "\u2018Awaj\u0101n el Gharb\u012b",
        "\u2018Awj\u0101n al Gharb\u012b"
    ],
    "wof:name":"`Awjan al Gharbi",
    "wof:placetype":"locality"
},
  "geometry": {"coordinates":[36.06531,32.02332],"type":"Point"}
}