{
  "type": "Feature",
  "properties": {
    "gn:admin1_code":"18",
    "gn:asciiname":"`Amrawah",
    "gn:country_code":"JO",
    "gn:dem":422,
    "gn:feature_class":"P",
    "gn:feature_code":"PPL",
    "gn:name":"\u2018Amr\u0101wah",
    "gn:population":0,
    "gn:timezone":"Asia/Amman",
    "iso:country":"JO",
    "name:ara_x_preferred":[
        "\u0639\u0645\u0631\u0627\u0648\u0629"
    ],
    "name:und_x_variant":[
        "\u2018Amr\u0101wa",
        "\u2018Amr\u0101wah"
    ],
    "wof:name":"`Amrawah",
    "wof:placetype":"locality"
},
  "geometry": {"coordinates":[35.93569,32.68642],"type":"Point"}
}