{
  "type": "Feature",
  "properties": {
    "gn:admin1_code":"15",
    "gn:asciiname":"Al Jubayyah",
    "gn:country_code":"JO",
    "gn:dem":1051,
    "gn:feature_class":"P",
    "gn:feature_code":"PPL",
    "gn:name":"Al Jubayyah",
    "gn:population":0,
    "gn:timezone":"Asia/Amman",
    "iso:country":"JO",
    "name:ara_x_preferred":[
        "\u0627\u0644\u062c\u0628\u064a\u0629"
    ],
    "wof:name":"Al Jubayyah",
    "wof:placetype":"locality"
},
  "geometry": {"coordinates":[36.78896,32.29423],"type":"Point"}
}