{
  "type": "Feature",
  "properties": {
    "gn:admin1_code":"02",
    "gn:asciiname":"Ash Shunah al Jadidah",
    "gn:country_code":"JO",
    "gn:dem":-209,
    "gn:feature_class":"P",
    "gn:feature_code":"PPL",
    "gn:name":"Ash Sh\u016bnah al Jad\u012bdah",
    "gn:population":0,
    "gn:timezone":"Asia/Amman",
    "iso:country":"JO",
    "name:ara_x_preferred":[
        "\u0627\u0644\u0634\u0648\u0646\u0629 \u0627\u0644\u062c\u062f\u064a\u062f\u0629"
    ],
    "name:und_x_variant":[
        "Ash Sh\u016bnah al Jad\u012bdah"
    ],
    "wof:name":"Ash Shunah al Jadidah",
    "wof:placetype":"locality"
},
  "geometry": {"coordinates":[35.60957,31.91315],"type":"Point"}
}