{
  "type": "Feature",
  "properties": {
    "gn:admin1_code":"02",
    "gn:asciiname":"Al `Arus",
    "gn:country_code":"JO",
    "gn:dem":-320,
    "gn:feature_class":"P",
    "gn:feature_code":"PPL",
    "gn:name":"Al \u2018Ar\u016bs",
    "gn:population":0,
    "gn:timezone":"Asia/Amman",
    "iso:country":"JO",
    "name:ara_x_preferred":[
        "\u0627\u0644\u0639\u0631\u0648\u0633"
    ],
    "name:fas_x_preferred":[
        "\u0627\u0644\u0639\u0631\u0648\u0633"
    ],
    "name:nno_x_preferred":[
        "Al `Arus"
    ],
    "name:und_x_variant":[
        "Al \u2018Ar\u016bs"
    ],
    "wof:name":"Al `Arus",
    "wof:placetype":"locality"
},
  "geometry": {"coordinates":[35.59309000000001,31.80022],"type":"Point"}
}