{
  "type": "Feature",
  "properties": {
    "gn:admin1_code":"12",
    "gn:asciiname":"Al `Aliyah",
    "gn:country_code":"JO",
    "gn:dem":804,
    "gn:feature_class":"P",
    "gn:feature_code":"PPL",
    "gn:name":"Al \u2018\u0100liyah",
    "gn:population":0,
    "gn:timezone":"Asia/Amman",
    "iso:country":"JO",
    "name:ara_x_preferred":[
        "\u0627\u0644\u0639\u0627\u0644\u064a\u0629"
    ],
    "name:und_x_variant":[
        "Al \u2018\u0100liyah"
    ],
    "wof:name":"Al `Aliyah",
    "wof:placetype":"locality"
},
  "geometry": {"coordinates":[35.8137,30.89972],"type":"Point"}
}