{
  "type": "Feature",
  "properties": {
    "gn:admin1_code":"12",
    "gn:asciiname":"Al Husayn",
    "gn:country_code":"JO",
    "gn:dem":1044,
    "gn:feature_class":"P",
    "gn:feature_code":"PPL",
    "gn:name":"Al \u1e28usayn",
    "gn:population":0,
    "gn:timezone":"Asia/Amman",
    "iso:country":"JO",
    "name:ara_x_preferred":[
        "\u0627\u0644\u062d\u0633\u064a\u0646"
    ],
    "name:und_x_variant":[
        "Al \u1e28usayn"
    ],
    "wof:name":"Al Husayn",
    "wof:placetype":"locality"
},
  "geometry": {"coordinates":[35.57891,30.82938],"type":"Point"}
}