{
  "type": "Feature",
  "properties": {
    "gn:admin1_code":"02",
    "gn:asciiname":"As Sawalihah",
    "gn:country_code":"JO",
    "gn:dem":-218,
    "gn:feature_class":"P",
    "gn:feature_code":"PPL",
    "gn:name":"A\u015f \u015eaw\u0101li\u1e29ah",
    "gn:population":0,
    "gn:timezone":"Asia/Amman",
    "iso:country":"JO",
    "name:ara_x_preferred":[
        "\u0627\u0644\u0635\u0648\u0627\u0644\u062d\u0629"
    ],
    "name:und_x_variant":[
        "E\u1e63 \u1e62aw\u0101li\u1e25a",
        "A\u015f \u015eaw\u0101li\u1e29ah"
    ],
    "wof:name":"As Sawalihah",
    "wof:placetype":"locality"
},
  "geometry": {"coordinates":[35.6224,32.18281],"type":"Point"}
}