{
  "type": "Feature",
  "properties": {
    "gn:admin1_code":"15",
    "gn:asciiname":"Al Buwaydah ash Sharqiyah",
    "gn:country_code":"JO",
    "gn:dem":756,
    "gn:feature_class":"P",
    "gn:feature_code":"PPL",
    "gn:name":"Al Buway\u1e11ah ash Sharq\u012byah",
    "gn:population":0,
    "gn:timezone":"Asia/Amman",
    "iso:country":"JO",
    "name:ara_x_preferred":[
        "\u0627\u0644\u0628\u0648\u064a\u0636\u0629 \u0627\u0644\u0634\u0631\u0642\u064a\u0629"
    ],
    "name:und_x_variant":[
        "Al Buway\u1e11ah ash Sharq\u012byah"
    ],
    "wof:name":"Al Buwaydah ash Sharqiyah",
    "wof:placetype":"locality"
},
  "geometry": {"coordinates":[36.16115,32.34198],"type":"Point"}
}