{
  "type": "Feature",
  "properties": {
    "gn:admin1_code":"09",
    "gn:asciiname":"Al Mazra`ah",
    "gn:country_code":"JO",
    "gn:dem":228,
    "gn:feature_class":"P",
    "gn:feature_code":"PPLL",
    "gn:name":"Al Mazra\u2018ah",
    "gn:population":0,
    "gn:timezone":"Asia/Amman",
    "iso:country":"JO",
    "name:ara_x_preferred":[
        "\u0627\u0644\u0645\u0632\u0631\u0639\u0629"
    ],
    "name:und_x_variant":[
        "Al Mazra\u2018ah"
    ],
    "wof:name":"Al Mazra`ah",
    "wof:placetype":"locality"
},
  "geometry": {"coordinates":[35.82492,31.42103],"type":"Point"}
}