{
  "type": "Feature",
  "properties": {
    "gn:admin1_code":"02",
    "gn:asciiname":"Abu az Zighan",
    "gn:country_code":"JO",
    "gn:dem":-194,
    "gn:feature_class":"P",
    "gn:feature_code":"PPL",
    "gn:name":"Ab\u016b az Z\u012bgh\u0101n",
    "gn:population":0,
    "gn:timezone":"Asia/Amman",
    "iso:country":"JO",
    "name:ara_x_preferred":[
        "\u0627\u0628\u0648 \u0627\u0644\u0632\u064a\u063a\u0627\u0646"
    ],
    "name:und_x_variant":[
        "Abu ez Zigh\u0101n",
        "Ab\u016b az Z\u012bgh\u0101n"
    ],
    "wof:name":"Abu az Zighan",
    "wof:placetype":"locality"
},
  "geometry": {"coordinates":[35.64079,32.18833],"type":"Point"}
}