{
  "type": "Feature",
  "properties": {
    "gn:admin1_code":"18",
    "gn:asciiname":"Biyarat al `Asal",
    "gn:country_code":"JO",
    "gn:dem":690,
    "gn:feature_class":"P",
    "gn:feature_code":"PPL",
    "gn:name":"Biy\u0101r\u0101t al \u2018Asal",
    "gn:population":0,
    "gn:timezone":"Asia/Amman",
    "iso:country":"JO",
    "name:ara_x_preferred":[
        "\u0628\u064a\u0627\u0631\u0627\u062a \u0627\u0644\u0639\u0633\u0644"
    ],
    "name:und_x_variant":[
        "Biy\u0101r\u0101t al \u2018Asal"
    ],
    "wof:name":"Biyarat al `Asal",
    "wof:placetype":"locality"
},
  "geometry": {"coordinates":[35.90436,32.46534],"type":"Point"}
}