{
  "type": "Feature",
  "properties": {
    "gn:admin1_code":"15",
    "gn:asciiname":"Hamid",
    "gn:country_code":"JO",
    "gn:dem":668,
    "gn:feature_class":"P",
    "gn:feature_code":"PPL",
    "gn:name":"\u1e28am\u012bd",
    "gn:population":0,
    "gn:timezone":"Asia/Amman",
    "iso:country":"JO",
    "name:ara_x_preferred":[
        "\u062d\u0645\u064a\u062f"
    ],
    "name:cat_x_preferred":[
        "H\u00e0mid"
    ],
    "name:deu_x_preferred":[
        "Hamid"
    ],
    "name:rus_x_preferred":[
        "\u0425\u0430\u043c\u0438\u0434"
    ],
    "name:ukr_x_preferred":[
        "\u0425\u0430\u043c\u0435\u0434"
    ],
    "name:und_x_variant":[
        "\u1e28am\u012bd"
    ],
    "wof:name":"Hamid",
    "wof:placetype":"locality"
},
  "geometry": {"coordinates":[36.00556,32.25723],"type":"Point"}
}