{
  "type": "Feature",
  "properties": {
    "iso:country":"JO",
    "name:ara_x_preferred":[
        "Hay Zahran"
    ],
    "qs:gn_adm0_cc":"JO",
    "qs:gn_local":250441,
    "qs:gn_nam_loc":"\u0639\u0645\u0627\u0646, \u0639\u0645\u0627\u0646, \u0639\u0645\u0627\u0646, JO",
    "qs:gn_namadm1":"16",
    "qs:local_max":2492,
    "qs:local_sum":10909,
    "qs:localhoods":30,
    "qs:name":"Hay Zahran",
    "qs:name_adm0":"\u0627\u0644\u0623\u0631\u062f\u0646",
    "qs:name_adm1":"\u0639\u0645\u0627\u0646",
    "qs:name_adm2":"\u0639\u0645\u0627\u0646",
    "qs:name_local":"\u0639\u0645\u0627\u0646",
    "qs:photo_max":347,
    "qs:photo_sum":885,
    "qs:placetype":"Suburb",
    "qs:quad_count":30,
    "qs:woe_adm0":23424860,
    "qs:woe_adm1":20070289,
    "qs:woe_adm2":56438163,
    "qs:woe_lau":0,
    "qs:woe_local":1968902,
    "qs:woe_ver":"7.10.0",
    "wof:lang":[
        "ara"
    ],
    "wof:name":"Hay Zahran",
    "wof:placetype":"neighbourhood"
},
  "geometry": {"coordinates":[35.88595,31.947053],"type":"Point"}
}