{
  "type": "Feature",
  "properties": {
    "gn:admin1_code":"09",
    "gn:asciiname":"Mirwad",
    "gn:cc2":"JO",
    "gn:country_code":"JO",
    "gn:dem":1146,
    "gn:feature_class":"P",
    "gn:feature_code":"PPL",
    "gn:name":"Mirwad",
    "gn:population":0,
    "gn:timezone":"Asia/Amman",
    "iso:country":"JO",
    "name:und_x_variant":[
        "Merwed",
        "Mirwid",
        "Mirwad"
    ],
    "wof:name":"Mirwad",
    "wof:placetype":"locality"
},
  "geometry": {"coordinates":[35.72444,31.10417],"type":"Point"}
}