{
  "type": "Feature",
  "properties": {
    "gn:admin1_code":"18",
    "gn:asciiname":"Hawfa",
    "gn:country_code":"JO",
    "gn:dem":343,
    "gn:feature_class":"P",
    "gn:feature_code":"PPL",
    "gn:name":"\u1e28awf\u0101",
    "gn:population":0,
    "gn:timezone":"Asia/Amman",
    "iso:country":"JO",
    "name:ara_x_preferred":[
        "\u062d\u0648\u0641\u0627"
    ],
    "name:und_x_variant":[
        "\u1e24auf\u0101",
        "\u1e28awfah",
        "Hofa",
        "\u1e28awf\u0101"
    ],
    "wof:name":"Hawfa",
    "wof:placetype":"locality"
},
  "geometry": {"coordinates":[35.71093,32.57091],"type":"Point"}
}