{
  "type": "Feature",
  "properties": {
    "gn:admin1_code":"21",
    "gn:asciiname":"Dibbat Hanut",
    "gn:country_code":"JO",
    "gn:dem":1187,
    "gn:feature_class":"P",
    "gn:feature_code":"PPL",
    "gn:name":"Dibbat \u1e28\u0101n\u016bt",
    "gn:population":0,
    "gn:timezone":"Asia/Amman",
    "iso:country":"JO",
    "name:ara_x_preferred":[
        "\u062f\u0628\u0629 \u062d\u0627\u0646\u0648\u062a"
    ],
    "name:und_x_variant":[
        "Dibbat \u1e28\u0101n\u016bt"
    ],
    "wof:name":"Dibbat Hanut",
    "wof:placetype":"locality"
},
  "geometry": {"coordinates":[35.46019000000001,29.96833],"type":"Point"}
}