{
  "type": "Feature",
  "properties": {
    "gn:admin1_code":"18",
    "gn:asciiname":"Al Muzayrib",
    "gn:country_code":"JO",
    "gn:dem":530,
    "gn:feature_class":"P",
    "gn:feature_code":"PPL",
    "gn:name":"Al Muzayr\u012bb",
    "gn:population":0,
    "gn:timezone":"Asia/Amman",
    "iso:country":"JO",
    "name:ara_x_preferred":[
        "\u0627\u0644\u0645\u0632\u064a\u0631\u064a\u0628"
    ],
    "name:und_x_variant":[
        "Al Muzayr\u012bb"
    ],
    "wof:name":"Al Muzayrib",
    "wof:placetype":"locality"
},
  "geometry": {"coordinates":[35.82360999999999,32.65322],"type":"Point"}
}