{
  "type": "Feature",
  "properties": {
    "gn:admin1_code":"02",
    "gn:asciiname":"Wadi an Naqah",
    "gn:country_code":"JO",
    "gn:dem":1085,
    "gn:feature_class":"P",
    "gn:feature_code":"PPL",
    "gn:name":"W\u0101d\u012b an N\u0101qah",
    "gn:population":0,
    "gn:timezone":"Asia/Amman",
    "iso:country":"JO",
    "name:ara_x_preferred":[
        "\u0648\u0627\u062f\u064a \u0627\u0644\u0646\u0627\u0642\u0629"
    ],
    "name:und_x_variant":[
        "W\u0101d\u012b an N\u0101qah"
    ],
    "wof:name":"Wadi an Naqah",
    "wof:placetype":"locality"
},
  "geometry": {"coordinates":[35.72214,32.08179000000001],"type":"Point"}
}