{
  "type": "Feature",
  "properties": {
    "gn:admin1_code":"15",
    "gn:asciiname":"Umm Butmah",
    "gn:country_code":"JO",
    "gn:dem":859,
    "gn:feature_class":"P",
    "gn:feature_code":"PPL",
    "gn:name":"Umm Bu\u0163mah",
    "gn:population":0,
    "gn:timezone":"Asia/Amman",
    "iso:country":"JO",
    "name:ara_x_preferred":[
        "\u0627\u0645 \u0628\u0637\u0645\u0629"
    ],
    "name:und_x_variant":[
        "Umm Bu\u0163mah"
    ],
    "wof:name":"Umm Butmah",
    "wof:placetype":"locality"
},
  "geometry": {"coordinates":[36.07298,32.34815],"type":"Point"}
}