{
  "type": "Feature",
  "properties": {
    "gn:admin1_code":"18",
    "gn:asciiname":"Kafr `An",
    "gn:country_code":"JO",
    "gn:dem":442,
    "gn:feature_class":"P",
    "gn:feature_code":"PPL",
    "gn:name":"Kafr \u2018\u0100n",
    "gn:population":0,
    "gn:timezone":"Asia/Amman",
    "iso:country":"JO",
    "name:ara_x_preferred":[
        "\u0643\u0641\u0631 \u0639\u0627\u0646"
    ],
    "name:und_x_variant":[
        "Kufr \u2018\u0100n",
        "Kafr \u2018\u0100n"
    ],
    "wof:name":"Kafr `An",
    "wof:placetype":"locality"
},
  "geometry": {"coordinates":[35.76215999999999,32.55206],"type":"Point"}
}