{
  "type": "Feature",
  "properties": {
    "iso:country":"JO",
    "name:ara_x_preferred":[
        "\u0633\u062d\u0627\u0628"
    ],
    "name:deu_x_preferred":[
        "Sahab"
    ],
    "name:eng_x_preferred":[
        "Sahab"
    ],
    "name:fas_x_preferred":[
        "\u0633\u062d\u0627\u0628"
    ],
    "name:fra_x_preferred":[
        "Sahab"
    ],
    "name:mzn_x_preferred":[
        "\u0633\u062d\u0627\u0628"
    ],
    "name:nld_x_preferred":[
        "Sahab"
    ],
    "name:nno_x_preferred":[
        "Sahab i Jordan"
    ],
    "name:pol_x_preferred":[
        "Sahab"
    ],
    "name:rus_x_preferred":[
        "\u0421\u0430\u0445\u0430\u0431"
    ],
    "name:spa_x_preferred":[
        "Sahab"
    ],
    "name:tur_x_preferred":[
        "Saheb"
    ],
    "name:unk_x_variant":[
        "Sehab"
    ],
    "name:urd_x_preferred":[
        "\u0636\u0644\u0639 \u0633\u062d\u0627\u0628"
    ],
    "qs:gn_country":"JO",
    "qs:gn_fcode":"PPL",
    "qs:gn_pop":40241,
    "qs:name":"\u0633\u062d\u0627\u0628",
    "qs:name_adm0":"\u0627\u0644\u0623\u0631\u062f\u0646",
    "qs:name_adm1":"\u0639\u0645\u0627\u0646",
    "qs:photos":0,
    "qs:photos_1k":0,
    "qs:photos_9k":0,
    "qs:photos_9r":0,
    "qs:photos_all":0,
    "qs:photos_sr":0,
    "qs:placetype":"Town",
    "qs:pop_sr":"7",
    "qs:woe_adm0":23424860,
    "wof:name":"\u0633\u062d\u0627\u0628",
    "wof:placetype":"locality",
    "wof:population":40241
},
  "geometry": {"coordinates":[36.00501,31.87207],"type":"Point"}
}