{
  "type": "Feature",
  "properties": {
    "gn:admin1_code":"15",
    "gn:asciiname":"Nayifah",
    "gn:country_code":"JO",
    "gn:dem":804,
    "gn:feature_class":"P",
    "gn:feature_code":"PPL",
    "gn:name":"N\u0101yifah",
    "gn:population":0,
    "gn:timezone":"Asia/Amman",
    "iso:country":"JO",
    "name:ara_x_preferred":[
        "\u0646\u0627\u064a\u0641\u0629"
    ],
    "name:und_x_variant":[
        "N\u0101yifah"
    ],
    "wof:name":"Nayifah",
    "wof:placetype":"locality"
},
  "geometry": {"coordinates":[36.61915,32.22231],"type":"Point"}
}