{
  "type": "Feature",
  "properties": {
    "gn:admin1_code":"21",
    "gn:asciiname":"Tutun",
    "gn:country_code":"JO",
    "gn:dem":774,
    "gn:feature_class":"P",
    "gn:feature_code":"PPL",
    "gn:name":"Tutun",
    "gn:population":0,
    "gn:timezone":"Asia/Amman",
    "iso:country":"JO",
    "name:ara_x_preferred":[
        "\u062a\u062a\u0646"
    ],
    "wof:name":"Tutun",
    "wof:placetype":"locality"
},
  "geometry": {"coordinates":[35.21004,29.42976],"type":"Point"}
}