{
  "type": "Feature",
  "properties": {
    "gn:country":"JO",
    "gn:fcode":"PPL",
    "gn:pop":14000,
    "iso:country":"JO",
    "name:ara_x_preferred":[
        "W\u0101d\u012b M\u016bs\u00e1"
    ],
    "name:ara_x_variant":[
        "\u0648\u0627\u062f\u064a \u0645\u0648\u0633\u0649",
        "\u0628\u062a\u0631\u0627"
    ],
    "name:eng_x_preferred":[
        "Petra"
    ],
    "name:rus_x_preferred":[
        "\u041f\u0435\u0442\u0440\u0430"
    ],
    "name:unk_x_variant":[
        "Alj\u012b"
    ],
    "qs:name":"Petra",
    "qs:photos_9r":0,
    "qs:photos_sr":0,
    "qs:pop_sr":"6",
    "wd:wordcount":5210,
    "wof:name":"Petra",
    "wof:placetype":"locality",
    "wof:population":14000
},
  "geometry": {"coordinates":[35.47933,30.32221],"type":"Point"}
}