{
  "type": "Feature",
  "properties": {
    "gn:admin1_code":"09",
    "gn:asciiname":"As Samra'",
    "gn:country_code":"JO",
    "gn:dem":884,
    "gn:feature_class":"P",
    "gn:feature_code":"PPL",
    "gn:name":"As Samr\u0101\u2019",
    "gn:population":0,
    "gn:timezone":"Asia/Amman",
    "iso:country":"JO",
    "name:und_x_variant":[
        "Samr\u0101",
        "Khirbat es Samra",
        "As Samr\u0101\u2019"
    ],
    "wof:name":"As Samra'",
    "wof:placetype":"locality"
},
  "geometry": {"coordinates":[35.75,31.36667000000001],"type":"Point"}
}