{
  "type": "Feature",
  "properties": {
    "gn:admin1_code":"22",
    "gn:asciiname":"Ar Rashayidah",
    "gn:country_code":"JO",
    "gn:dem":540,
    "gn:feature_class":"P",
    "gn:feature_code":"PPL",
    "gn:name":"Ar Rash\u0101yidah",
    "gn:population":0,
    "gn:timezone":"Asia/Amman",
    "iso:country":"JO",
    "name:ara_x_preferred":[
        "\u0627\u0644\u0631\u0634\u0627\u064a\u062f\u0629"
    ],
    "name:und_x_variant":[
        "Rash\u0101da",
        "Er Rash\u0101yida",
        "Ar Rash\u0101dah",
        "Er Rashada",
        "Ar Rash\u0101\u2019idah",
        "Ar Rash\u0101yidah"
    ],
    "wof:name":"Ar Rashayidah",
    "wof:placetype":"locality"
},
  "geometry": {"coordinates":[35.89797,32.24339000000001],"type":"Point"}
}