{
  "type": "Feature",
  "properties": {
    "gn:admin1_code":"09",
    "gn:asciiname":"Abu ash Shahm",
    "gn:cc2":"JO",
    "gn:country_code":"JO",
    "gn:dem":959,
    "gn:feature_class":"P",
    "gn:feature_code":"PPL",
    "gn:name":"Ab\u016b ash Sha\u1e29m",
    "gn:population":0,
    "gn:timezone":"Asia/Amman",
    "iso:country":"JO",
    "name:und_x_variant":[
        "Ab\u016b esh Sha\u1e25m",
        "Ab\u016b ash Sha\u1e29m"
    ],
    "wof:name":"Abu ash Shahm",
    "wof:placetype":"locality"
},
  "geometry": {"coordinates":[35.75,31.13333],"type":"Point"}
}