{
  "type": "Feature",
  "properties": {
    "gn:admin1_code":"18",
    "gn:asciiname":"Jijjin",
    "gn:country_code":"JO",
    "gn:dem":393,
    "gn:feature_class":"P",
    "gn:feature_code":"PPL",
    "gn:name":"Jijj\u012bn",
    "gn:population":0,
    "gn:timezone":"Asia/Amman",
    "iso:country":"JO",
    "name:ara_x_preferred":[
        "Jijj\u012bn"
    ],
    "name:ara_x_variant":[
        "\u062c\u062c\u064a\u0646"
    ],
    "name:und_x_variant":[
        "Jejjin",
        "Jejin"
    ],
    "wof:name":"Jijjin",
    "wof:placetype":"locality"
},
  "geometry": {"coordinates":[35.76958,32.58613],"type":"Point"}
}