{
  "type": "Feature",
  "properties": {
    "gn:admin1_code":"15",
    "gn:asciiname":"Rujm Sab` ash Shamali",
    "gn:country_code":"JO",
    "gn:dem":761,
    "gn:feature_class":"P",
    "gn:feature_code":"PPL",
    "gn:name":"Rujm Sab\u2018 ash Sham\u0101l\u012b",
    "gn:population":0,
    "gn:timezone":"Asia/Amman",
    "iso:country":"JO",
    "name:ara_x_preferred":[
        "\u0631\u062c\u0645 \u0633\u0628\u0639 \u0627\u0644\u0634\u0645\u0627\u0644\u064a"
    ],
    "name:und_x_variant":[
        "Rujm Sab\u2018 ash Sham\u0101l\u012b"
    ],
    "wof:name":"Rujm Sab` ash Shamali",
    "wof:placetype":"locality"
},
  "geometry": {"coordinates":[36.14872,32.36348],"type":"Point"}
}