{
  "type": "Feature",
  "properties": {
    "iso:country":"JO",
    "qs:gn_pop":0,
    "qs:name":"Jarash Ref. Camp",
    "qs:name_adm0":"\u0627\u0644\u0623\u0631\u062f\u0646",
    "qs:name_adm1":"\u062c\u0631\u0634",
    "qs:photos":9,
    "qs:photos_1k":2,
    "qs:photos_9k":1,
    "qs:photos_9r":1,
    "qs:photos_all":9,
    "qs:photos_sr":1,
    "qs:placetype":"Town",
    "qs:pop_sr":"0",
    "qs:woe_adm0":23424860,
    "wof:name":"Jarash Ref. Camp",
    "wof:placetype":"locality"
},
  "geometry": {"coordinates":[35.917053,32.275522],"type":"Point"}
}