{
  "type": "Feature",
  "properties": {
    "gn:admin1_code":"02",
    "gn:asciiname":"Di`am",
    "gn:country_code":"JO",
    "gn:dem":927,
    "gn:feature_class":"P",
    "gn:feature_code":"PPL",
    "gn:name":"Di\u2018am",
    "gn:population":0,
    "gn:timezone":"Asia/Amman",
    "iso:country":"JO",
    "name:ara_x_preferred":[
        "\u062f\u0639\u0645"
    ],
    "name:und_x_variant":[
        "Da\u2018am",
        "Di\u2018am"
    ],
    "wof:name":"Di`am",
    "wof:placetype":"locality"
},
  "geometry": {"coordinates":[35.74377,32.0895],"type":"Point"}
}