{
  "type": "Feature",
  "properties": {
    "gn:admin1_code":"23",
    "gn:asciiname":"Dulaylat al Hamayidah",
    "gn:country_code":"JO",
    "gn:dem":764,
    "gn:feature_class":"P",
    "gn:feature_code":"PPL",
    "gn:name":"Dulaylat al \u1e28am\u0101yidah",
    "gn:population":0,
    "gn:timezone":"Asia/Amman",
    "iso:country":"JO",
    "name:ara_x_preferred":[
        "\u062f\u0644\u064a\u0644\u0629 \u0627\u0644\u062d\u0645\u0627\u064a\u062f\u0629"
    ],
    "name:nno_x_preferred":[
        "Dulaylat al Hama'idah"
    ],
    "name:pol_x_preferred":[
        "Dulajlat al-Hamajida"
    ],
    "name:sqi_x_preferred":[
        "Dulaylat al Hama'idah"
    ],
    "name:und_x_variant":[
        "Khirbat ed-Deleil\u00e2t el-Gharb\u00eeyeh",
        "Duleilit el Ham\u0101yida",
        "Deleilet el-Hemaide",
        "Duleilat el \u1e24am\u0101yida",
        "Dulaylat al \u1e28am\u0101\u2019idah",
        "Dulaylat al \u1e28am\u0101yidah"
    ],
    "wof:name":"Dulaylat al Hamayidah",
    "wof:placetype":"locality"
},
  "geometry": {"coordinates":[35.79058,31.61933],"type":"Point"}
}