{
  "type": "Feature",
  "properties": {
    "gn:admin1_code":"09",
    "gn:asciiname":"Ad Dimnah",
    "gn:country_code":"JO",
    "gn:dem":970,
    "gn:feature_class":"P",
    "gn:feature_code":"PPL",
    "gn:name":"Ad Dimnah",
    "gn:population":0,
    "gn:timezone":"Asia/Amman",
    "iso:country":"JO",
    "name:und_x_variant":[
        "Dimna",
        "Ed Dimna",
        "El Demne",
        "Ad Dimnah"
    ],
    "wof:name":"Ad Dimnah",
    "wof:placetype":"locality"
},
  "geometry": {"coordinates":[35.7026,31.292],"type":"Point"}
}