{
  "type": "Feature",
  "properties": {
    "gn:admin1_code":"15",
    "gn:asciiname":"An Nimrah",
    "gn:country_code":"JO",
    "gn:dem":607,
    "gn:feature_class":"P",
    "gn:feature_code":"PPL",
    "gn:name":"An Nimrah",
    "gn:population":0,
    "gn:timezone":"Asia/Amman",
    "iso:country":"JO",
    "name:ara_x_preferred":[
        "\u0627\u0644\u0646\u0645\u0631\u0629"
    ],
    "name:und_x_variant":[
        "En Nimra",
        "An Nimrah"
    ],
    "wof:name":"An Nimrah",
    "wof:placetype":"locality"
},
  "geometry": {"coordinates":[36.14161,32.21799],"type":"Point"}
}