{
  "type": "Feature",
  "properties": {
    "gn:admin1_code":"19",
    "gn:asciiname":"Al `Uwaynah",
    "gn:country_code":"JO",
    "gn:dem":1133,
    "gn:feature_class":"P",
    "gn:feature_code":"PPL",
    "gn:name":"Al \u2018Uwaynah",
    "gn:population":0,
    "gn:timezone":"Asia/Amman",
    "iso:country":"JO",
    "name:ara_x_preferred":[
        "\u0627\u0644\u0639\u0648\u064a\u0646\u0629"
    ],
    "name:und_x_variant":[
        "Al \u2018Uwaynah"
    ],
    "wof:name":"Al `Uwaynah",
    "wof:placetype":"locality"
},
  "geometry": {"coordinates":[35.70624,30.2973],"type":"Point"}
}