{
  "type": "Feature",
  "properties": {
    "gn:admin1_code":"09",
    "gn:asciiname":"Wadi Sararah",
    "gn:country_code":"JO",
    "gn:dem":1021,
    "gn:feature_class":"P",
    "gn:feature_code":"PPL",
    "gn:name":"W\u0101d\u012b \u015ear\u0101rah",
    "gn:population":0,
    "gn:timezone":"Asia/Amman",
    "iso:country":"JO",
    "name:ara_x_preferred":[
        "\u0648\u0627\u062f\u064a \u0635\u0631\u0627\u0631\u0629"
    ],
    "name:und_x_variant":[
        "Sar\u0101ra",
        "W\u0101d\u012b \u015ear\u0101rah"
    ],
    "wof:name":"Wadi Sararah",
    "wof:placetype":"locality"
},
  "geometry": {"coordinates":[35.67273,31.0191],"type":"Point"}
}