{
  "type": "Feature",
  "properties": {
    "gn:admin1_code":"18",
    "gn:asciiname":"Samad",
    "gn:country_code":"JO",
    "gn:dem":903,
    "gn:feature_class":"P",
    "gn:feature_code":"PPL",
    "gn:name":"\u015eamad",
    "gn:population":0,
    "gn:timezone":"Asia/Amman",
    "iso:country":"JO",
    "name:ara_x_preferred":[
        "\u0635\u0645\u062f"
    ],
    "name:und_x_variant":[
        "\u015eamad"
    ],
    "wof:name":"Samad",
    "wof:placetype":"locality"
},
  "geometry": {"coordinates":[35.83244000000001,32.45981],"type":"Point"}
}