{
  "type": "Feature",
  "properties": {
    "iso:country":"JO",
    "name:ara_x_preferred":[
        "Burm\u0101"
    ],
    "name:ara_x_variant":[
        "\u0628\u0631\u0645\u0627"
    ],
    "qs:gn_country":"JO",
    "qs:gn_fcode":"PPL",
    "qs:gn_pop":4735,
    "qs:name":"\u0628\u0631\u0645\u0627",
    "qs:name_adm0":"\u0627\u0644\u0623\u0631\u062f\u0646",
    "qs:name_adm1":"\u062c\u0631\u0634",
    "qs:photos":0,
    "qs:photos_1k":0,
    "qs:photos_9k":1,
    "qs:photos_9r":1,
    "qs:photos_all":1,
    "qs:photos_sr":0,
    "qs:placetype":"Town",
    "qs:pop_sr":"4",
    "qs:woe_adm0":23424860,
    "wof:name":"\u0628\u0631\u0645\u0627",
    "wof:placetype":"locality",
    "wof:population":4735
},
  "geometry": {"coordinates":[35.78394,32.2199],"type":"Point"}
}