{
  "type": "Feature",
  "properties": {
    "gn:admin1_code":"09",
    "gn:asciiname":"As Salmani",
    "gn:country_code":"JO",
    "gn:dem":-180,
    "gn:feature_class":"P",
    "gn:feature_code":"PPL",
    "gn:name":"As Salm\u0101n\u012b",
    "gn:population":0,
    "gn:timezone":"Asia/Amman",
    "iso:country":"JO",
    "name:ara_x_preferred":[
        "\u0627\u0644\u0633\u0644\u0645\u0627\u0646\u064a"
    ],
    "name:und_x_variant":[
        "As Salm\u0101n\u012b"
    ],
    "wof:name":"As Salmani",
    "wof:placetype":"locality"
},
  "geometry": {"coordinates":[35.38491,30.8298],"type":"Point"}
}