{
  "type": "Feature",
  "properties": {
    "gn:admin1_code":"17",
    "gn:asciiname":"Wad`ah",
    "gn:country_code":"JO",
    "gn:dem":464,
    "gn:feature_class":"P",
    "gn:feature_code":"PPLL",
    "gn:name":"Wad\u2018ah",
    "gn:population":0,
    "gn:timezone":"Asia/Amman",
    "iso:country":"JO",
    "name:ara_x_preferred":[
        "\u0648\u062f\u0639\u0629"
    ],
    "name:und_x_variant":[
        "Khirbat Wad\u2018a",
        "Khirbat Wada\u2018ah",
        "Wad\u2018ah",
        "Khirbat Wad\u2018ah"
    ],
    "wof:name":"Wad`ah",
    "wof:placetype":"locality"
},
  "geometry": {"coordinates":[36.04971,32.14859000000001],"type":"Point"}
}