{
  "type": "Feature",
  "properties": {
    "gn:admin1_code":"17",
    "gn:asciiname":"`Awjan ash Sharqi",
    "gn:country_code":"JO",
    "gn:dem":606,
    "gn:feature_class":"P",
    "gn:feature_code":"PPL",
    "gn:name":"\u2018Awj\u0101n ash Sharq\u012b",
    "gn:population":0,
    "gn:timezone":"Asia/Amman",
    "iso:country":"JO",
    "name:und_x_variant":[
        "Awaj\u0101n esh Sharqi",
        "\u2018Awj\u0101n ash Sharq\u012b"
    ],
    "wof:name":"`Awjan ash Sharqi",
    "wof:placetype":"locality"
},
  "geometry": {"coordinates":[36.07892,32.02709],"type":"Point"}
}