{
  "type": "Feature",
  "properties": {
    "gn:admin1_code":"22",
    "gn:asciiname":"An Na`imiyah",
    "gn:country_code":"JO",
    "gn:dem":977,
    "gn:feature_class":"P",
    "gn:feature_code":"PPL",
    "gn:name":"An Na\u2018\u012bm\u012byah",
    "gn:population":0,
    "gn:timezone":"Asia/Amman",
    "iso:country":"JO",
    "name:ara_x_preferred":[
        "\u0627\u0644\u0646\u0639\u064a\u0645\u064a\u0629"
    ],
    "name:und_x_variant":[
        "An Na\u2018\u012bm\u012byah",
        "An Nu\u2018aym\u012byah"
    ],
    "wof:name":"An Na`imiyah",
    "wof:placetype":"locality"
},
  "geometry": {"coordinates":[35.94568,32.32524],"type":"Point"}
}