{
  "type": "Feature",
  "properties": {
    "gn:admin1_code":"15",
    "gn:asciiname":"Khisha` al Qinn",
    "gn:country_code":"JO",
    "gn:dem":1134,
    "gn:feature_class":"P",
    "gn:feature_code":"PPL",
    "gn:name":"Khish\u0101\u2018 al Qinn",
    "gn:population":0,
    "gn:timezone":"Asia/Amman",
    "iso:country":"JO",
    "name:ara_x_preferred":[
        "\u062e\u0634\u0627\u0639 \u0627\u0644\u0642\u0646"
    ],
    "name:und_x_variant":[
        "Khish\u0101\u2018 al Qinn"
    ],
    "wof:name":"Khisha` al Qinn",
    "wof:placetype":"locality"
},
  "geometry": {"coordinates":[36.90679,32.32671],"type":"Point"}
}