{
  "type": "Feature",
  "properties": {
    "gn:admin1_code":"23",
    "gn:asciiname":"Tajammu` al Musay`idat",
    "gn:country_code":"JO",
    "gn:dem":641,
    "gn:feature_class":"P",
    "gn:feature_code":"PPL",
    "gn:name":"Tajammu\u2018 al Musay\u2018id\u0101t",
    "gn:population":0,
    "gn:timezone":"Asia/Amman",
    "iso:country":"JO",
    "name:ara_x_preferred":[
        "\u062a\u062c\u0645\u0639 \u0627\u0644\u0645\u0633\u064a\u0639\u062f\u0627\u062a"
    ],
    "name:und_x_variant":[
        "Tajammu\u2018 al Musay\u2018id\u0101t"
    ],
    "wof:name":"Tajammu` al Musay`idat",
    "wof:placetype":"locality"
},
  "geometry": {"coordinates":[35.79389000000001,31.58753],"type":"Point"}
}