{
  "type": "Feature",
  "properties": {
    "gn:admin1_code":"15",
    "gn:asciiname":"Iskan al Manshiyah",
    "gn:country_code":"JO",
    "gn:dem":860,
    "gn:feature_class":"P",
    "gn:feature_code":"PPL",
    "gn:name":"Isk\u0101n al Mansh\u012byah",
    "gn:population":0,
    "gn:timezone":"Asia/Amman",
    "iso:country":"JO",
    "name:ara_x_preferred":[
        "\u0627\u0633\u0643\u0627\u0646 \u0627\u0644\u0645\u0646\u0634\u064a\u0629"
    ],
    "name:und_x_variant":[
        "Isk\u0101n al Mansh\u012byah"
    ],
    "wof:name":"Iskan al Manshiyah",
    "wof:placetype":"locality"
},
  "geometry": {"coordinates":[36.06197,32.37061],"type":"Point"}
}