{
  "type": "Feature",
  "properties": {
    "gn:admin1_code":"18",
    "gn:asciiname":"Hobras",
    "gn:country_code":"JO",
    "gn:dem":483,
    "gn:feature_class":"P",
    "gn:feature_code":"PPL",
    "gn:name":"Hobras",
    "gn:population":0,
    "gn:timezone":"Asia/Amman",
    "iso:country":"JO",
    "name:ara_x_preferred":[
        "\u1e28ubr\u0101\u015f"
    ],
    "name:ara_x_variant":[
        "\u062d\u0628\u0631\u0627\u0635"
    ],
    "wof:name":"Hobras",
    "wof:placetype":"locality"
},
  "geometry": {"coordinates":[35.84185,32.6695],"type":"Point"}
}