{
  "type": "Feature",
  "properties": {
    "gn:admin1_code":"09",
    "gn:asciiname":"Al `Umariyah",
    "gn:country_code":"JO",
    "gn:dem":1224,
    "gn:feature_class":"P",
    "gn:feature_code":"PPL",
    "gn:name":"Al \u2018Umar\u012byah",
    "gn:population":0,
    "gn:timezone":"Asia/Amman",
    "iso:country":"JO",
    "name:ara_x_preferred":[
        "\u0627\u0644\u0639\u0645\u0631\u064a\u0629"
    ],
    "name:ara_x_variant":[
        "\u062f\u0644\u064a\u0642\u0629"
    ],
    "name:und_x_variant":[
        "Duleiqa",
        "Deleiqe",
        "Dulayqah",
        "Al \u2018Umar\u012byah",
        "Al \u2018Umariyya"
    ],
    "wof:name":"Al `Umariyah",
    "wof:placetype":"locality"
},
  "geometry": {"coordinates":[35.72383,31.03523],"type":"Point"}
}