{
  "type": "Feature",
  "properties": {
    "gn:admin1_code":"20",
    "gn:asciiname":"Khirbat as Sakhinah",
    "gn:country_code":"JO",
    "gn:dem":718,
    "gn:feature_class":"P",
    "gn:feature_code":"PPL",
    "gn:name":"Khirbat as S\u0101khinah",
    "gn:population":0,
    "gn:timezone":"Asia/Amman",
    "iso:country":"JO",
    "name:und_x_variant":[
        "Khirbat es S\u0101khina",
        "Khirbat as S\u0101khinah"
    ],
    "wof:name":"Khirbat as Sakhinah",
    "wof:placetype":"locality"
},
  "geometry": {"coordinates":[35.75186,32.24567],"type":"Point"}
}