{
  "type": "Feature",
  "properties": {
    "iso:country":"JO",
    "name:ara_x_preferred":[
        "\u0632\u062d\u0631"
    ],
    "name:unk_x_variant":[
        "Za\u1e29ar"
    ],
    "qs:gn_country":"JO",
    "qs:gn_fcode":"PPL",
    "qs:gn_pop":4150,
    "qs:name":"\u0632\u062d\u0631",
    "qs:name_adm0":"\u0627\u0644\u0623\u0631\u062f\u0646",
    "qs:name_adm1":"\u0625\u0631\u0628\u062f",
    "qs:photos":0,
    "qs:photos_1k":0,
    "qs:photos_9k":0,
    "qs:photos_9r":0,
    "qs:photos_all":0,
    "qs:photos_sr":0,
    "qs:placetype":"Town",
    "qs:pop_sr":"4",
    "qs:woe_adm0":23424860,
    "wof:name":"\u0632\u062d\u0631",
    "wof:placetype":"locality",
    "wof:population":4150
},
  "geometry": {"coordinates":[35.7775,32.56667],"type":"Point"}
}