{
  "type": "Feature",
  "properties": {
    "gn:admin1_code":"19",
    "gn:asciiname":"Khashm al Batra'",
    "gn:country_code":"JO",
    "gn:dem":1252,
    "gn:feature_class":"P",
    "gn:feature_code":"PPL",
    "gn:name":"Khashm al Batr\u0101\u2019",
    "gn:population":0,
    "gn:timezone":"Asia/Amman",
    "iso:country":"JO",
    "name:ara_x_preferred":[
        "\u062e\u0634\u0645 \u0627\u0644\u0628\u062a\u0631\u0627\u0621"
    ],
    "name:und_x_variant":[
        "Khashm al Batr\u0101\u2019"
    ],
    "wof:name":"Khashm al Batra'",
    "wof:placetype":"locality"
},
  "geometry": {"coordinates":[35.69201,29.94784000000001],"type":"Point"}
}