{
  "type": "Feature",
  "properties": {
    "iso:country":"JO",
    "qs:gn_pop":0,
    "qs:name":"Siyagha",
    "qs:name_adm0":"\u0627\u0644\u0623\u0631\u062f\u0646",
    "qs:name_adm1":"\u0645\u0627\u062f\u0628\u0627",
    "qs:photos":256,
    "qs:photos_1k":52,
    "qs:photos_9k":1,
    "qs:photos_9r":4,
    "qs:photos_all":256,
    "qs:photos_sr":5,
    "qs:placetype":"Town",
    "qs:pop_sr":"0",
    "qs:woe_adm0":23424860,
    "wof:name":"Siyagha",
    "wof:placetype":"locality"
},
  "geometry": {"coordinates":[35.714235,31.76725],"type":"Point"}
}