{
  "type": "Feature",
  "properties": {
    "gn:admin1_code":"23",
    "gn:asciiname":"Umm an Ni`aj",
    "gn:country_code":"JO",
    "gn:dem":754,
    "gn:feature_class":"P",
    "gn:feature_code":"PPLL",
    "gn:name":"Umm an Ni\u2018\u0101j",
    "gn:population":0,
    "gn:timezone":"Asia/Amman",
    "iso:country":"JO",
    "name:ara_x_preferred":[
        "\u0627\u0645 \u0627\u0644\u0646\u0639\u0627\u062c"
    ],
    "name:und_x_variant":[
        "Umm an Ni\u2018\u0101j"
    ],
    "wof:name":"Umm an Ni`aj",
    "wof:placetype":"locality"
},
  "geometry": {"coordinates":[35.75529,31.48558],"type":"Point"}
}