{
  "type": "Feature",
  "properties": {
    "gn:admin1_code":"02",
    "gn:asciiname":"Bayt al Husayni",
    "gn:country_code":"JO",
    "gn:dem":-233,
    "gn:feature_class":"P",
    "gn:feature_code":"PPL",
    "gn:name":"Bayt al \u1e28usayn\u012b",
    "gn:population":0,
    "gn:timezone":"Asia/Amman",
    "iso:country":"JO",
    "name:und_x_variant":[
        "Beit el Huseini",
        "Bayt al \u1e28usayn\u012b"
    ],
    "wof:name":"Bayt al Husayni",
    "wof:placetype":"locality"
},
  "geometry": {"coordinates":[35.6319,32.18385],"type":"Point"}
}