{
  "type": "Feature",
  "properties": {
    "gn:admin1_code":"09",
    "gn:asciiname":"`Alaqan",
    "gn:country_code":"JO",
    "gn:dem":926,
    "gn:feature_class":"P",
    "gn:feature_code":"PPL",
    "gn:name":"\u2018Alaq\u0101n",
    "gn:population":0,
    "gn:timezone":"Asia/Amman",
    "iso:country":"JO",
    "name:ara_x_preferred":[
        "\u0639\u0644\u0627\u0642\u0627\u0646"
    ],
    "name:und_x_variant":[
        "\u2018Alaq\u0101n"
    ],
    "wof:name":"`Alaqan",
    "wof:placetype":"locality"
},
  "geometry": {"coordinates":[35.64585,31.14221],"type":"Point"}
}