{
  "type": "Feature",
  "properties": {
    "gn:admin1_code":"09",
    "gn:asciiname":"Dhat Ra's",
    "gn:country_code":"JO",
    "gn:dem":1142,
    "gn:feature_class":"P",
    "gn:feature_code":"PPL",
    "gn:name":"Dh\u0101t Ra\u2019s",
    "gn:population":0,
    "gn:timezone":"Asia/Amman",
    "iso:country":"JO",
    "name:ara_x_preferred":[
        "\u0630\u0627\u062a \u0631\u0623\u0633"
    ],
    "name:und_x_variant":[
        "Dat Ras",
        "Dh\u0101t Ra\u2019s"
    ],
    "wof:name":"Dhat Ra's",
    "wof:placetype":"locality"
},
  "geometry": {"coordinates":[35.76307,31.00112],"type":"Point"}
}