{
  "type": "Feature",
  "properties": {
    "iso:country":"JO",
    "name:ara_x_preferred":[
        "\u0628\u064a\u062a \u064a\u0627\u0641\u0627"
    ],
    "name:unk_x_variant":[
        "Beit Y\u0101f\u0101"
    ],
    "qs:gn_country":"JO",
    "qs:gn_fcode":"PPL",
    "qs:gn_pop":7788,
    "qs:name":"\u0628\u064a\u062a \u064a\u0627\u0641\u0627",
    "qs:name_adm0":"\u0627\u0644\u0623\u0631\u062f\u0646",
    "qs:name_adm1":"\u0625\u0631\u0628\u062f",
    "qs:photos":0,
    "qs:photos_1k":0,
    "qs:photos_9k":1,
    "qs:photos_9r":1,
    "qs:photos_all":11,
    "qs:photos_sr":0,
    "qs:placetype":"Town",
    "qs:pop_sr":"5",
    "qs:woe_adm0":23424860,
    "wof:name":"\u0628\u064a\u062a \u064a\u0627\u0641\u0627",
    "wof:placetype":"locality",
    "wof:population":7788
},
  "geometry": {"coordinates":[35.7883,32.51737],"type":"Point"}
}