{
  "type": "Feature",
  "properties": {
    "gn:admin1_code":"02",
    "gn:asciiname":"Al Midmar",
    "gn:country_code":"JO",
    "gn:dem":625,
    "gn:feature_class":"P",
    "gn:feature_code":"PPL",
    "gn:name":"Al Mi\u1e11m\u0101r",
    "gn:population":0,
    "gn:timezone":"Asia/Amman",
    "iso:country":"JO",
    "name:ara_x_preferred":[
        "\u0627\u0644\u0645\u0636\u0645\u0627\u0631"
    ],
    "name:und_x_variant":[
        "Rujm el Mi\u1e0dhm\u0101r",
        "Rujm al Mi\u1e11m\u0101r",
        "Al Mi\u1e11m\u0101r"
    ],
    "wof:name":"Al Midmar",
    "wof:placetype":"locality"
},
  "geometry": {"coordinates":[35.81792,32.0698],"type":"Point"}
}