{
  "type": "Feature",
  "properties": {
    "gn:admin1_code":"19",
    "gn:asciiname":"Al Hayy",
    "gn:country_code":"JO",
    "gn:dem":1567,
    "gn:feature_class":"P",
    "gn:feature_code":"PPL",
    "gn:name":"Al \u1e28ayy",
    "gn:population":0,
    "gn:timezone":"Asia/Amman",
    "iso:country":"JO",
    "name:ara_x_preferred":[
        "\u0627\u0644\u062d\u064a"
    ],
    "name:ara_x_variant":[
        "\u0627\u0633\u0643\u0627\u0646 \u0627\u0644\u062d\u064a"
    ],
    "name:und_x_variant":[
        "\u1e28ayy",
        "El Hai",
        "\u1e24ai",
        "Al \u1e28ayy",
        "Isk\u0101n al \u1e28ayy"
    ],
    "wof:name":"Al Hayy",
    "wof:placetype":"locality"
},
  "geometry": {"coordinates":[35.50684000000001,30.36391],"type":"Point"}
}