{
  "type": "Feature",
  "properties": {
    "gn:admin1_code":"18",
    "gn:asciiname":"Natifah",
    "gn:country_code":"JO",
    "gn:dem":666,
    "gn:feature_class":"P",
    "gn:feature_code":"PPL",
    "gn:name":"N\u0101\u0163ifah",
    "gn:population":0,
    "gn:timezone":"Asia/Amman",
    "iso:country":"JO",
    "name:ara_x_preferred":[
        "\u0646\u0627\u0637\u0641\u0629"
    ],
    "name:nno_x_preferred":[
        "Natifah"
    ],
    "name:und_x_variant":[
        "Natfe",
        "N\u0101\u1e6difa",
        "N\u0101\u0163ifah"
    ],
    "wof:name":"Natifah",
    "wof:placetype":"locality"
},
  "geometry": {"coordinates":[35.8204,32.5204],"type":"Point"}
}