{
  "type": "Feature",
  "properties": {
    "gn:admin1_code":"22",
    "gn:asciiname":"Ar Rahmaniyah",
    "gn:country_code":"JO",
    "gn:dem":678,
    "gn:feature_class":"P",
    "gn:feature_code":"PPL",
    "gn:name":"Ar Ra\u1e29m\u0101n\u012byah",
    "gn:population":0,
    "gn:timezone":"Asia/Amman",
    "iso:country":"JO",
    "name:ara_x_preferred":[
        "\u0627\u0644\u0631\u062d\u0645\u0627\u0646\u064a\u0629"
    ],
    "name:und_x_variant":[
        "Ar Ra\u1e29m\u0101n\u012byah"
    ],
    "wof:name":"Ar Rahmaniyah",
    "wof:placetype":"locality"
},
  "geometry": {"coordinates":[35.86908,32.15715],"type":"Point"}
}