{
  "type": "Feature",
  "properties": {
    "gn:admin1_code":"09",
    "gn:asciiname":"Al Hamidiyah",
    "gn:country_code":"JO",
    "gn:dem":993,
    "gn:feature_class":"P",
    "gn:feature_code":"PPL",
    "gn:name":"Al \u1e28\u0101mid\u012byah",
    "gn:population":0,
    "gn:timezone":"Asia/Amman",
    "iso:country":"JO",
    "name:ara_x_preferred":[
        "\u0627\u0644\u062d\u0627\u0645\u062f\u064a\u0629"
    ],
    "name:und_x_variant":[
        "Al \u1e28\u0101mid\u012byah"
    ],
    "wof:name":"Al Hamidiyah",
    "wof:placetype":"locality"
},
  "geometry": {"coordinates":[35.90427000000001,30.92167],"type":"Point"}
}