{
  "type": "Feature",
  "properties": {
    "gn:admin1_code":"16",
    "gn:asciiname":"Sumiya",
    "gn:country_code":"JO",
    "gn:dem":451,
    "gn:feature_class":"P",
    "gn:feature_code":"PPLL",
    "gn:name":"S\u016bmiy\u0101",
    "gn:population":0,
    "gn:timezone":"Asia/Amman",
    "iso:country":"JO",
    "name:ara_x_preferred":[
        "\u0633\u0648\u0645\u064a\u0627"
    ],
    "name:und_x_variant":[
        "Sumia",
        "S\u016bmiy\u0101"
    ],
    "wof:name":"Sumiya",
    "wof:placetype":"locality"
},
  "geometry": {"coordinates":[35.76667,31.81667],"type":"Point"}
}