{
  "type": "Feature",
  "properties": {
    "gn:admin1_code":"22",
    "gn:asciiname":"Nawwarah",
    "gn:country_code":"JO",
    "gn:dem":717,
    "gn:feature_class":"P",
    "gn:feature_code":"PPL",
    "gn:name":"Naww\u0101rah",
    "gn:population":0,
    "gn:timezone":"Asia/Amman",
    "iso:country":"JO",
    "name:ara_x_preferred":[
        "\u0646\u0648\u0627\u0631\u0629"
    ],
    "name:und_x_variant":[
        "Naww\u0101rah"
    ],
    "wof:name":"Nawwarah",
    "wof:placetype":"locality"
},
  "geometry": {"coordinates":[35.8748,32.16696],"type":"Point"}
}