{
  "type": "Feature",
  "properties": {
    "gn:admin1_code":"23",
    "gn:asciiname":"Murayjimat Ibn Hamid",
    "gn:country_code":"JO",
    "gn:dem":755,
    "gn:feature_class":"P",
    "gn:feature_code":"PPL",
    "gn:name":"Murayjimat Ibn \u1e28\u0101mid",
    "gn:population":0,
    "gn:timezone":"Asia/Amman",
    "iso:country":"JO",
    "name:nno_x_preferred":[
        "Murayjimat Ibn Hamid"
    ],
    "name:sqi_x_preferred":[
        "Murayjimat Ibn Hamid"
    ],
    "name:und_x_variant":[
        "Mereijmet Ibn Hamed",
        "Mureijimat \u012abn \u1e24\u0101mid",
        "Murayjimat Ibn \u1e28\u0101mid"
    ],
    "wof:name":"Murayjimat Ibn Hamid",
    "wof:placetype":"locality"
},
  "geometry": {"coordinates":[35.77763,31.65808],"type":"Point"}
}