{
  "type": "Feature",
  "properties": {
    "gn:admin1_code":"20",
    "gn:asciiname":"As Suq",
    "gn:country_code":"JO",
    "gn:dem":737,
    "gn:feature_class":"P",
    "gn:feature_code":"PPL",
    "gn:name":"As S\u016bq",
    "gn:population":0,
    "gn:timezone":"Asia/Amman",
    "iso:country":"JO",
    "name:und_x_variant":[
        "Es S\u016bq",
        "As S\u016bq"
    ],
    "wof:name":"As Suq",
    "wof:placetype":"locality"
},
  "geometry": {"coordinates":[35.75909,32.24686],"type":"Point"}
}