{
  "type": "Feature",
  "properties": {
    "gn:country":"JO",
    "gn:fcode":"PPL",
    "gn:population":6082,
    "iso:country":"JO",
    "name:und_x_variant":[
        "Rimon"
    ],
    "qs:name":"Raym\u016bn",
    "qs:photos_9r":0,
    "qs:photos_sr":0,
    "qs:pop_sr":"5",
    "wof:name":"Raym\u016bn",
    "wof:placetype":"locality",
    "wof:population":6082
},
  "geometry": {"coordinates":[35.82532,32.28339],"type":"Point"}
}