{
  "type": "Feature",
  "properties": {
    "gn:admin1_code":"18",
    "gn:asciiname":"Muhammad Salih",
    "gn:country_code":"JO",
    "gn:dem":-271,
    "gn:feature_class":"P",
    "gn:feature_code":"PPL",
    "gn:name":"Mu\u1e29ammad \u015e\u0101li\u1e29",
    "gn:population":0,
    "gn:timezone":"Asia/Amman",
    "iso:country":"JO",
    "name:ara_x_preferred":[
        "\u0645\u062d\u0645\u062f \u0635\u0627\u0644\u062d"
    ],
    "name:fra_x_preferred":[
        "Muhammad Solih"
    ],
    "name:rus_x_preferred":[
        "\u041c\u0443\u0445\u0430\u043c\u043c\u0430\u0434 \u0421\u0430\u043b\u0438\u0445"
    ],
    "name:tur_x_preferred":[
        "Muhammed Salih"
    ],
    "name:und_x_variant":[
        "Mu\u1e29ammad \u015e\u0101li\u1e29"
    ],
    "wof:name":"Muhammad Salih",
    "wof:placetype":"locality"
},
  "geometry": {"coordinates":[35.56293,32.51896],"type":"Point"}
}