{
  "type": "Feature",
  "properties": {
    "gn:admin1_code":"09",
    "gn:asciiname":"Al Khalidiyah",
    "gn:country_code":"JO",
    "gn:dem":1176,
    "gn:feature_class":"P",
    "gn:feature_code":"PPL",
    "gn:name":"Al Kh\u0101lid\u012byah",
    "gn:population":0,
    "gn:timezone":"Asia/Amman",
    "iso:country":"JO",
    "name:aar_x_preferred":[
        "Umm Zab\u0101yir"
    ],
    "name:ara_x_preferred":[
        "\u0627\u0644\u062e\u0627\u0644\u062f\u064a\u0629"
    ],
    "name:ara_x_variant":[
        "\u0627\u0645 \u0632\u0628\u0627\u064a\u0631"
    ],
    "name:und_x_variant":[
        "Um Zebayer",
        "Um Zab\u0101yir",
        "Umm Zab\u0101\u2019ir",
        "Al Kh\u0101lid\u012byah",
        "Al Kh\u0101lidiyya"
    ],
    "wof:name":"Al Khalidiyah",
    "wof:placetype":"locality"
},
  "geometry": {"coordinates":[35.73820999999999,31.02982],"type":"Point"}
}