{
  "type": "Feature",
  "properties": {
    "gn:admin1_code":"15",
    "gn:asciiname":"Dahl",
    "gn:country_code":"JO",
    "gn:dem":643,
    "gn:feature_class":"P",
    "gn:feature_code":"PPL",
    "gn:name":"Da\u1e29l",
    "gn:population":0,
    "gn:timezone":"Asia/Amman",
    "iso:country":"JO",
    "name:ara_x_preferred":[
        "\u062f\u062d\u0644"
    ],
    "name:bel_x_preferred":[
        "\u0414\u0430\u043b\u044c"
    ],
    "name:ceb_x_preferred":[
        "Dahl"
    ],
    "name:ces_x_preferred":[
        "Dahl"
    ],
    "name:deu_x_preferred":[
        "Dahl"
    ],
    "name:fin_x_preferred":[
        "Dahl"
    ],
    "name:fra_x_preferred":[
        "Dahl"
    ],
    "name:ita_x_preferred":[
        "Dahl"
    ],
    "name:jpn_x_preferred":[
        "\u30c0\u30fc\u30eb"
    ],
    "name:kor_x_preferred":[
        "\ub2ec"
    ],
    "name:nld_x_preferred":[
        "Dahl"
    ],
    "name:nor_x_preferred":[
        "Dahl"
    ],
    "name:pol_x_preferred":[
        "Dahl"
    ],
    "name:rus_x_preferred":[
        "\u0414\u0430\u043b\u044c"
    ],
    "name:spa_x_preferred":[
        "Dahl"
    ],
    "name:swe_x_preferred":[
        "Dahl"
    ],
    "name:ukr_x_preferred":[
        "\u0414\u0430\u043b\u044c"
    ],
    "name:und_x_variant":[
        "Dahel",
        "Da\u1e29al",
        "Khirbat Dahal",
        "Khirbat Da\u1e29l",
        "Da\u1e29l"
    ],
    "wof:name":"Dahl",
    "wof:placetype":"locality"
},
  "geometry": {"coordinates":[35.97518,32.27349],"type":"Point"}
}