{
  "type": "Feature",
  "properties": {
    "gn:admin1_code":"16",
    "gn:asciiname":"Umm Nuwwarah",
    "gn:country_code":"JO",
    "gn:dem":792,
    "gn:feature_class":"P",
    "gn:feature_code":"PPL",
    "gn:name":"Umm Nuww\u0101rah",
    "gn:population":0,
    "gn:timezone":"Asia/Amman",
    "iso:country":"JO",
    "name:und_x_variant":[
        "Umm Nuww\u0101rah",
        "Um Nuwwara",
        "Um Noware",
        "Umm N\u016bw\u0101rah"
    ],
    "wof:name":"Umm Nuwwarah",
    "wof:placetype":"locality"
},
  "geometry": {"coordinates":[35.79683,31.93197],"type":"Point"}
}