{
  "type": "Feature",
  "properties": {
    "gn:admin1_code":"02",
    "gn:asciiname":"Muthallath al `Aridah",
    "gn:country_code":"JO",
    "gn:dem":-229,
    "gn:feature_class":"P",
    "gn:feature_code":"PPL",
    "gn:name":"Muthallath al \u2018\u0100ri\u1e11ah",
    "gn:population":0,
    "gn:timezone":"Asia/Amman",
    "iso:country":"JO",
    "name:ara_x_preferred":[
        "\u0645\u062b\u0644\u062b \u0627\u0644\u0639\u0627\u0631\u0636\u0629"
    ],
    "name:und_x_variant":[
        "Muthallath el \u2018\u0100rda",
        "Muthallath al \u2018\u0100ri\u1e11ah"
    ],
    "wof:name":"Muthallath al `Aridah",
    "wof:placetype":"locality"
},
  "geometry": {"coordinates":[35.61218,32.14074],"type":"Point"}
}