{
  "type": "Feature",
  "properties": {
    "iso:country":"JO",
    "qs:gn_pop":0,
    "qs:name":"Ghor Nemreen",
    "qs:name_adm0":"\u0627\u0644\u0623\u0631\u062f\u0646",
    "qs:name_adm1":"\u0627\u0644\u0628\u0644\u0642\u0627\u0621",
    "qs:photos":502,
    "qs:photos_1k":102,
    "qs:photos_9k":2,
    "qs:photos_9r":5,
    "qs:photos_all":502,
    "qs:photos_sr":7,
    "qs:placetype":"Town",
    "qs:pop_sr":"0",
    "qs:woe_adm0":23424860,
    "wof:name":"Ghor Nemreen",
    "wof:placetype":"locality"
},
  "geometry": {"coordinates":[35.553474,31.8369595],"type":"Point"}
}