{
  "type": "Feature",
  "properties": {
    "gn:admin1_code":"22",
    "gn:asciiname":"Umm Qantarah al Gharbiyah",
    "gn:country_code":"JO",
    "gn:dem":677,
    "gn:feature_class":"P",
    "gn:feature_code":"PPL",
    "gn:name":"Umm Qan\u0163arah al Gharb\u012byah",
    "gn:population":0,
    "gn:timezone":"Asia/Amman",
    "iso:country":"JO",
    "name:ara_x_preferred":[
        "\u0623\u0645 \u0642\u0646\u0637\u0631\u0629 \u0627\u0644\u063a\u0631\u0628\u064a\u0629"
    ],
    "name:und_x_variant":[
        "Um Qantara",
        "Um Qantera",
        "Umm Qan\u0163arah",
        "Umm Qan\u0163arah al Gharb\u012byah"
    ],
    "wof:name":"Umm Qantarah al Gharbiyah",
    "wof:placetype":"locality"
},
  "geometry": {"coordinates":[35.94165,32.26463],"type":"Point"}
}