{
  "type": "Feature",
  "properties": {
    "iso:country":"JO",
    "name:ara_x_preferred":[
        "\u0627\u0644\u0642\u0648\u064a\u0631\u0629"
    ],
    "name:unk_x_variant":[
        "El Quweira"
    ],
    "qs:gn_country":"JO",
    "qs:gn_fcode":"PPL",
    "qs:gn_pop":7372,
    "qs:name":"Al Quwayrah",
    "qs:name_adm0":"\u0627\u0644\u0623\u0631\u062f\u0646",
    "qs:name_adm1":"\u0627\u0644\u0639\u0642\u0628\u0629",
    "qs:photos":82,
    "qs:photos_1k":17,
    "qs:photos_9k":1,
    "qs:photos_9r":3,
    "qs:photos_all":82,
    "qs:photos_sr":3,
    "qs:placetype":"Town",
    "qs:pop_sr":"5",
    "qs:woe_adm0":23424860,
    "wof:name":"Al Quwayrah",
    "wof:placetype":"locality",
    "wof:population":7372
},
  "geometry": {"coordinates":[35.3116,29.80045],"type":"Point"}
}