{
  "type": "Feature",
  "properties": {
    "gn:admin1_code":"02",
    "gn:asciiname":"Al Manashsh",
    "gn:country_code":"JO",
    "gn:dem":504,
    "gn:feature_class":"P",
    "gn:feature_code":"PPL",
    "gn:name":"Al Manashsh",
    "gn:population":0,
    "gn:timezone":"Asia/Amman",
    "iso:country":"JO",
    "name:ara_x_preferred":[
        "\u0627\u0644\u0645\u0646\u0634"
    ],
    "name:und_x_variant":[
        "El Manashsh",
        "Al Manashsh"
    ],
    "wof:name":"Al Manashsh",
    "wof:placetype":"locality"
},
  "geometry": {"coordinates":[35.82873,32.12734],"type":"Point"}
}