{
  "type": "Feature",
  "properties": {
    "gn:admin1_code":"18",
    "gn:asciiname":"Al Manshiyah",
    "gn:country_code":"JO",
    "gn:dem":-261,
    "gn:feature_class":"P",
    "gn:feature_code":"PPL",
    "gn:name":"Al Mansh\u012byah",
    "gn:population":0,
    "gn:timezone":"Asia/Amman",
    "iso:country":"JO",
    "name:ara_x_preferred":[
        "\u0627\u0644\u0645\u0646\u0634\u064a\u0629"
    ],
    "name:und_x_variant":[
        "Mansh\u012bya",
        "El Manshiya",
        "Al Mansh\u012byah"
    ],
    "wof:name":"Al Manshiyah",
    "wof:placetype":"locality"
},
  "geometry": {"coordinates":[35.57974,32.58552],"type":"Point"}
}