{
  "type": "Feature",
  "properties": {
    "gn:admin1_code":"18",
    "gn:asciiname":"Iskan as Sarir",
    "gn:country_code":"JO",
    "gn:dem":59,
    "gn:feature_class":"P",
    "gn:feature_code":"PPLL",
    "gn:name":"Isk\u0101n as Sar\u012br",
    "gn:population":0,
    "gn:timezone":"Asia/Amman",
    "iso:country":"JO",
    "name:ara_x_preferred":[
        "\u0627\u0633\u0643\u0627\u0646 \u0627\u0644\u0633\u0631\u064a\u0631"
    ],
    "name:und_x_variant":[
        "Isk\u0101n as Sar\u012br"
    ],
    "wof:name":"Iskan as Sarir",
    "wof:placetype":"locality"
},
  "geometry": {"coordinates":[35.69726,32.69579],"type":"Point"}
}