{
  "type": "Feature",
  "properties": {
    "gn:admin1_code":"02",
    "gn:asciiname":"Al Balawinah",
    "gn:country_code":"JO",
    "gn:dem":-161,
    "gn:feature_class":"P",
    "gn:feature_code":"PPL",
    "gn:name":"Al Bal\u0101winah",
    "gn:population":0,
    "gn:timezone":"Asia/Amman",
    "iso:country":"JO",
    "name:ara_x_preferred":[
        "\u0627\u0644\u0628\u0644\u0627\u0648\u0646\u0629"
    ],
    "name:und_x_variant":[
        "Al Bal\u0101winah"
    ],
    "wof:name":"Al Balawinah",
    "wof:placetype":"locality"
},
  "geometry": {"coordinates":[35.62393,32.24073],"type":"Point"}
}