{
  "type": "Feature",
  "properties": {
    "gn:admin1_code":"17",
    "gn:asciiname":"Al Mikhdhat",
    "gn:country_code":"JO",
    "gn:dem":505,
    "gn:feature_class":"P",
    "gn:feature_code":"PPL",
    "gn:name":"Al Mikhdh\u0101t",
    "gn:population":0,
    "gn:timezone":"Asia/Amman",
    "iso:country":"JO",
    "name:ara_x_preferred":[
        "\u0627\u0644\u0645\u062e\u0630\u0627\u062a"
    ],
    "name:und_x_variant":[
        "Al Mikhdh\u0101t"
    ],
    "wof:name":"Al Mikhdhat",
    "wof:placetype":"locality"
},
  "geometry": {"coordinates":[35.96749000000001,32.17742],"type":"Point"}
}