{
  "type": "Feature",
  "properties": {
    "gn:admin1_code":"19",
    "gn:asciiname":"Az Zaytunah",
    "gn:country_code":"JO",
    "gn:dem":1384,
    "gn:feature_class":"P",
    "gn:feature_code":"PPL",
    "gn:name":"Az Zayt\u016bnah",
    "gn:population":0,
    "gn:timezone":"Asia/Amman",
    "iso:country":"JO",
    "name:ara_x_preferred":[
        "\u0627\u0644\u0632\u064a\u062a\u0648\u0646\u0647"
    ],
    "name:und_x_variant":[
        "Az Zayt\u016bnah"
    ],
    "wof:name":"Az Zaytunah",
    "wof:placetype":"locality"
},
  "geometry": {"coordinates":[35.56898,30.48371],"type":"Point"}
}