{
  "type": "Feature",
  "properties": {
    "gn:admin1_code":"23",
    "gn:asciiname":"Umm Shujayrah al Gharbiyah",
    "gn:country_code":"JO",
    "gn:dem":727,
    "gn:feature_class":"P",
    "gn:feature_code":"PPL",
    "gn:name":"Umm Shujayrah al Gharb\u012byah",
    "gn:population":0,
    "gn:timezone":"Asia/Amman",
    "iso:country":"JO",
    "name:ara_x_preferred":[
        "\u0627\u0645 \u0634\u062c\u064a\u0631\u0629 \u0627\u0644\u063a\u0631\u0628\u064a\u0629"
    ],
    "name:nno_x_preferred":[
        "Umm Shujayrah al Gharbiyah"
    ],
    "name:sco_x_preferred":[
        "Umm Shujayrah al Gharbiyah"
    ],
    "name:sqi_x_preferred":[
        "Umm Shujayrah al Gharbiyah"
    ],
    "name:und_x_variant":[
        "Umm Shujeirat el Jam\u0101\u2019\u012bn",
        "Um Shojeire el Gharbiye",
        "Umm Shejeir\u00e2t el Gharb\u00eeyeh",
        "Um Shujeira el Gharb\u012bya",
        "Um Shojeira al Gharbiye",
        "Umm Shajara",
        "Umm Shujayrah al Gharb\u012byah"
    ],
    "wof:name":"Umm Shujayrah al Gharbiyah",
    "wof:placetype":"locality"
},
  "geometry": {"coordinates":[35.8455,31.51882],"type":"Point"}
}