{
  "type": "Feature",
  "properties": {
    "gn:admin1_code":"12",
    "gn:asciiname":"Al La`ban",
    "gn:country_code":"JO",
    "gn:dem":697,
    "gn:feature_class":"P",
    "gn:feature_code":"PPLL",
    "gn:name":"Al La\u2018b\u0101n",
    "gn:population":0,
    "gn:timezone":"Asia/Amman",
    "iso:country":"JO",
    "name:ara_x_preferred":[
        "\u0627\u0644\u0644\u0639\u0628\u0627\u0646"
    ],
    "name:und_x_variant":[
        "La\u2018b\u0101n",
        "Le\u2019ban",
        "Al La\u2018b\u0101n"
    ],
    "wof:name":"Al La`ban",
    "wof:placetype":"locality"
},
  "geometry": {"coordinates":[35.69993,30.90713],"type":"Point"}
}