{
  "type": "Feature",
  "properties": {
    "gn:country":"JO",
    "gn:fcode":"PPL",
    "gn:pop":18274,
    "iso:country":"JO",
    "name:unk_x_variant":[
        "Um el Semmaq"
    ],
    "qs:name":"Umm as Summ\u0101q",
    "qs:photos_9r":0,
    "qs:photos_sr":0,
    "qs:pop_sr":"6",
    "wof:name":"Umm as Summ\u0101q",
    "wof:placetype":"locality",
    "wof:population":18274
},
  "geometry": {"coordinates":[35.8543,31.88542],"type":"Point"}
}