{
  "type": "Feature",
  "properties": {
    "gn:admin1_code":"23",
    "gn:asciiname":"Miqla` al Khaznah",
    "gn:country_code":"JO",
    "gn:dem":711,
    "gn:feature_class":"P",
    "gn:feature_code":"PPL",
    "gn:name":"Miqla\u2018 al Khaznah",
    "gn:population":0,
    "gn:timezone":"Asia/Amman",
    "iso:country":"JO",
    "name:ara_x_preferred":[
        "\u0645\u0642\u0644\u0639 \u0627\u0644\u062e\u0632\u0646\u0629"
    ],
    "name:und_x_variant":[
        "Miqla\u2018 al Khaznah"
    ],
    "wof:name":"Miqla` al Khaznah",
    "wof:placetype":"locality"
},
  "geometry": {"coordinates":[35.76054,31.61698],"type":"Point"}
}