{
  "type": "Feature",
  "properties": {
    "gn:admin1_code":"09",
    "gn:asciiname":"Ad Dabbakah",
    "gn:country_code":"JO",
    "gn:dem":1237,
    "gn:feature_class":"P",
    "gn:feature_code":"PPL",
    "gn:name":"Ad Dabb\u0101kah",
    "gn:population":0,
    "gn:timezone":"Asia/Amman",
    "iso:country":"JO",
    "name:und_x_variant":[
        "Kheurbet ed Dabka",
        "Dabka",
        "Ad Dabkah",
        "Ed Dabb\u0101ka",
        "Ad Dabb\u0101kah"
    ],
    "wof:name":"Ad Dabbakah",
    "wof:placetype":"locality"
},
  "geometry": {"coordinates":[35.65405,31.06167],"type":"Point"}
}