{
  "type": "Feature",
  "properties": {
    "gn:admin1_code":"19",
    "gn:asciiname":"At Tumay`ah",
    "gn:country_code":"JO",
    "gn:dem":1301,
    "gn:feature_class":"P",
    "gn:feature_code":"PPL",
    "gn:name":"A\u0163 \u0162umay\u2018ah",
    "gn:population":0,
    "gn:timezone":"Asia/Amman",
    "iso:country":"JO",
    "name:ara_x_preferred":[
        "\u0627\u0644\u0637\u0645\u064a\u0639\u0629"
    ],
    "name:und_x_variant":[
        "A\u0163 \u0162umay\u2018ah"
    ],
    "wof:name":"At Tumay`ah",
    "wof:placetype":"locality"
},
  "geometry": {"coordinates":[35.59534,30.33972],"type":"Point"}
}