{
  "type": "Feature",
  "properties": {
    "gn:admin1_code":"17",
    "gn:asciiname":"Al Hasab",
    "gn:country_code":"JO",
    "gn:dem":479,
    "gn:feature_class":"P",
    "gn:feature_code":"PPL",
    "gn:name":"Al \u1e28a\u015fab",
    "gn:population":0,
    "gn:timezone":"Asia/Amman",
    "iso:country":"JO",
    "name:ara_x_preferred":[
        "\u0627\u0644\u062d\u0635\u0628"
    ],
    "name:und_x_variant":[
        "Al \u1e28a\u015fab"
    ],
    "wof:name":"Al Hasab",
    "wof:placetype":"locality"
},
  "geometry": {"coordinates":[36.00554,32.1845],"type":"Point"}
}