{
  "type": "Feature",
  "properties": {
    "gn:admin1_code":"18",
    "gn:asciiname":"`Aqraba",
    "gn:country_code":"JO",
    "gn:dem":375,
    "gn:feature_class":"P",
    "gn:feature_code":"PPL",
    "gn:name":"\u2018Aqrab\u0101",
    "gn:population":0,
    "gn:timezone":"Asia/Amman",
    "iso:country":"JO",
    "name:ara_x_preferred":[
        "\u0639\u0642\u0631\u0628\u0627"
    ],
    "name:und_x_variant":[
        "\u2018Agraba",
        "\u2018Aqrabah",
        "\u2018Aqrab\u0101"
    ],
    "wof:name":"`Aqraba",
    "wof:placetype":"locality"
},
  "geometry": {"coordinates":[35.7988,32.72896],"type":"Point"}
}