{
  "type": "Feature",
  "properties": {
    "gn:admin1_code":"02",
    "gn:asciiname":"Umm Sindiyanah",
    "gn:country_code":"JO",
    "gn:dem":595,
    "gn:feature_class":"P",
    "gn:feature_code":"PPL",
    "gn:name":"Umm Sindiy\u0101nah",
    "gn:population":0,
    "gn:timezone":"Asia/Amman",
    "iso:country":"JO",
    "name:ara_x_preferred":[
        "\u0623\u0645 \u0633\u0646\u062f\u064a\u0627\u0646\u0629"
    ],
    "name:und_x_variant":[
        "Umm Sindiy\u0101nah"
    ],
    "wof:name":"Umm Sindiyanah",
    "wof:placetype":"locality"
},
  "geometry": {"coordinates":[35.81264,32.09914000000001],"type":"Point"}
}