{
  "type": "Feature",
  "properties": {
    "gn:admin1_code":"20",
    "gn:asciiname":"Umm al Manabi`",
    "gn:country_code":"JO",
    "gn:dem":1052,
    "gn:feature_class":"P",
    "gn:feature_code":"PPL",
    "gn:name":"Umm al Man\u0101b\u012b\u2018",
    "gn:population":0,
    "gn:timezone":"Asia/Amman",
    "iso:country":"JO",
    "name:ara_x_preferred":[
        "\u0627\u0645 \u0627\u0644\u0645\u0646\u0627\u0628\u064a\u0639"
    ],
    "name:und_x_variant":[
        "Um el Man\u0101b\u012b\u2018",
        "Umm al Man\u0101b\u012b\u2018"
    ],
    "wof:name":"Umm al Manabi`",
    "wof:placetype":"locality"
},
  "geometry": {"coordinates":[35.7653,32.37288],"type":"Point"}
}