{
  "type": "Feature",
  "properties": {
    "gn:country":"JO",
    "gn:fcode":"PPL",
    "gn:pop":22581,
    "iso:country":"JO",
    "name:ara_x_preferred":[
        "\u0627\u0644\u0643\u0631\u0643"
    ],
    "name:arz_x_preferred":[
        "\u0627\u0644\u0643\u0631\u0643"
    ],
    "name:bul_x_preferred":[
        "\u041a\u0430\u0440\u0430\u043a"
    ],
    "name:cat_x_preferred":[
        "Al-Karak"
    ],
    "name:ces_x_preferred":[
        "Kerak"
    ],
    "name:deu_x_preferred":[
        "Kerak"
    ],
    "name:ell_x_preferred":[
        "\u0391\u03bb \u039a\u03b1\u03c1\u03ac\u03ba"
    ],
    "name:eng_x_preferred":[
        "Al Karak"
    ],
    "name:epo_x_preferred":[
        "Kerak"
    ],
    "name:eus_x_preferred":[
        "Karak"
    ],
    "name:fas_x_preferred":[
        "\u06a9\u0631\u06a9"
    ],
    "name:fra_x_preferred":[
        "Al-Karak"
    ],
    "name:heb_x_preferred":[
        "\u05db\u05e8\u05db"
    ],
    "name:hin_x_preferred":[
        "\u0905\u0932-\u0915\u0930\u093e\u0915"
    ],
    "name:ita_x_preferred":[
        "Al-Karak"
    ],
    "name:jpn_x_preferred":[
        "\u30ab\u30e9\u30af"
    ],
    "name:kaz_x_preferred":[
        "\u042d\u043b\u044c-\u041a\u0430\u0440\u0430\u043a"
    ],
    "name:kor_x_preferred":[
        "\uce74\ub77c\ud06c"
    ],
    "name:lit_x_preferred":[
        "Karakas"
    ],
    "name:mzn_x_preferred":[
        "\u06a9\u0631\u06a9"
    ],
    "name:nld_x_preferred":[
        "Kerak"
    ],
    "name:nno_x_preferred":[
        "Al Karak"
    ],
    "name:nob_x_preferred":[
        "Al Karak"
    ],
    "name:oci_x_preferred":[
        "Al-Karak"
    ],
    "name:pnb_x_preferred":[
        "\u06a9\u0631\u06a9"
    ],
    "name:pol_x_preferred":[
        "Al-Karak"
    ],
    "name:por_x_preferred":[
        "Al Karak"
    ],
    "name:rus_x_preferred":[
        "\u042d\u043b\u044c-\u041a\u0430\u0440\u0430\u043a"
    ],
    "name:spa_x_preferred":[
        "Al Karak"
    ],
    "name:sqi_x_preferred":[
        "Kerak"
    ],
    "name:srp_x_preferred":[
        "\u0415\u043b \u041a\u0430\u0440\u0430\u043a"
    ],
    "name:tur_x_preferred":[
        "El Karak"
    ],
    "name:ukr_x_preferred":[
        "\u0415\u043b\u044c-\u041a\u0430\u0440\u0430\u043a"
    ],
    "name:unk_x_variant":[
        "Al Karak"
    ],
    "name:urd_x_preferred":[
        "\u0627\u0644\u06a9\u0631\u06a9"
    ],
    "name:zho_x_preferred":[
        "\u5361\u62c9\u514b"
    ],
    "qs:name":"Q\u012br Mo\u0101v",
    "qs:photos_9r":0,
    "qs:photos_sr":0,
    "qs:pop_sr":"7",
    "wof:name":"Q\u012br Mo\u0101v",
    "wof:placetype":"locality",
    "wof:population":22581
},
  "geometry": {"coordinates":[35.69999,31.18248],"type":"Point"}
}