{
  "type": "Feature",
  "properties": {
    "gn:admin1_code":"19",
    "gn:asciiname":"Al Fardhakh",
    "gn:country_code":"JO",
    "gn:dem":1485,
    "gn:feature_class":"P",
    "gn:feature_code":"PPL",
    "gn:name":"Al Fardhakh",
    "gn:population":0,
    "gn:timezone":"Asia/Amman",
    "iso:country":"JO",
    "name:ara_x_preferred":[
        "\u0627\u0644\u0641\u0631\u0630\u062e"
    ],
    "name:und_x_variant":[
        "Fardhakh",
        "El Fardhakh",
        "Al Fardhakh"
    ],
    "wof:name":"Al Fardhakh",
    "wof:placetype":"locality"
},
  "geometry": {"coordinates":[35.51221,30.18867],"type":"Point"}
}