{
  "type": "Feature",
  "properties": {
    "gn:admin1_code":"18",
    "gn:asciiname":"Zubiya",
    "gn:country_code":"JO",
    "gn:dem":933,
    "gn:feature_class":"P",
    "gn:feature_code":"PPL",
    "gn:name":"Z\u016bbiy\u0101",
    "gn:population":0,
    "gn:timezone":"Asia/Amman",
    "iso:country":"JO",
    "name:ara_x_preferred":[
        "\u0632\u0648\u0628\u064a\u0627"
    ],
    "name:und_x_variant":[
        "Zubia",
        "Z\u016bbiy\u0101"
    ],
    "wof:name":"Zubiya",
    "wof:placetype":"locality"
},
  "geometry": {"coordinates":[35.77419000000001,32.4306],"type":"Point"}
}