{
  "type": "Feature",
  "properties": {
    "gn:admin1_code":"20",
    "gn:asciiname":"`Irjan",
    "gn:country_code":"JO",
    "gn:dem":651,
    "gn:feature_class":"P",
    "gn:feature_code":"PPLA3",
    "gn:name":"\u2018Irj\u0101n",
    "gn:population":0,
    "gn:timezone":"Asia/Amman",
    "iso:country":"JO",
    "name:ara_x_preferred":[
        "\u0639\u0631\u062c\u0627\u0646"
    ],
    "name:und_x_variant":[
        "\u2018Irj\u0101n",
        "Irj\u0101n"
    ],
    "wof:name":"`Irjan",
    "wof:placetype":"locality"
},
  "geometry": {"coordinates":[35.73345,32.39447],"type":"Point"}
}