{
  "type": "Feature",
  "properties": {
    "gn:admin1_code":"18",
    "gn:asciiname":"Khirbat ash Shaykh Muhammad",
    "gn:country_code":"JO",
    "gn:dem":-256,
    "gn:feature_class":"P",
    "gn:feature_code":"PPL",
    "gn:name":"Khirbat ash Shaykh Mu\u1e29ammad",
    "gn:population":0,
    "gn:timezone":"Asia/Jerusalem",
    "iso:country":"JO",
    "name:ara_x_preferred":[
        "\u062e\u0631\u0628\u0629 \u0627\u0644\u0634\u064a\u062e \u0645\u062d\u0645\u062f"
    ],
    "name:und_x_variant":[
        "Ash Shaykh Mu\u1e29ammad",
        "Khirbat Sheikh Muhammad",
        "Khirbet Sheikh Mo\u1e29ammad",
        "Khirbat ash Shaykh Mu\u1e29ammad"
    ],
    "wof:name":"Khirbat ash Shaykh Muhammad",
    "wof:placetype":"locality"
},
  "geometry": {"coordinates":[35.58395,32.49692],"type":"Point"}
}