{
  "type": "Feature",
  "properties": {
    "iso:country":"JO",
    "name:ara_x_preferred":[
        "\u0627\u064a\u062f\u0648\u0646"
    ],
    "name:eng_x_preferred":[
        "Aydoun"
    ],
    "qs:gn_pop":0,
    "qs:name":"\u0627\u064a\u062f\u0648\u0646",
    "qs:name_adm0":"\u0627\u0644\u0623\u0631\u062f\u0646",
    "qs:name_adm1":"\u0625\u0631\u0628\u062f",
    "qs:photos":7,
    "qs:photos_1k":1,
    "qs:photos_9k":1,
    "qs:photos_9r":1,
    "qs:photos_all":7,
    "qs:photos_sr":1,
    "qs:placetype":"Town",
    "qs:pop_sr":"0",
    "qs:woe_adm0":23424860,
    "wof:name":"Aydoun",
    "wof:placetype":"locality"
},
  "geometry": {"coordinates":[35.850277,32.520401],"type":"Point"}
}