{
  "type": "Feature",
  "properties": {
    "gn:admin1_code":"15",
    "gn:asciiname":"An Nuzhah",
    "gn:country_code":"JO",
    "gn:dem":737,
    "gn:feature_class":"P",
    "gn:feature_code":"PPL",
    "gn:name":"An Nuzhah",
    "gn:population":0,
    "gn:timezone":"Asia/Amman",
    "iso:country":"JO",
    "name:ara_x_preferred":[
        "\u0627\u0644\u0646\u0632\u0647\u0629"
    ],
    "wof:name":"An Nuzhah",
    "wof:placetype":"locality"
},
  "geometry": {"coordinates":[36.09345,32.25323],"type":"Point"}
}