{
  "type": "Feature",
  "properties": {
    "gn:admin1_code":"18",
    "gn:asciiname":"Al Mudhabirah",
    "gn:country_code":"JO",
    "gn:dem":576,
    "gn:feature_class":"P",
    "gn:feature_code":"PPL",
    "gn:name":"Al Mud\u1e29abirah",
    "gn:population":0,
    "gn:timezone":"Asia/Amman",
    "iso:country":"JO",
    "name:ara_x_preferred":[
        "\u0627\u0644\u0645\u062f\u062d\u0628\u0631\u0629"
    ],
    "name:und_x_variant":[
        "Al Mud\u1e29abirah"
    ],
    "wof:name":"Al Mudhabirah",
    "wof:placetype":"locality"
},
  "geometry": {"coordinates":[35.7107,32.39982],"type":"Point"}
}