{
  "type": "Feature",
  "properties": {
    "gn:admin1_code":"23",
    "gn:asciiname":"Al Mi`qar",
    "gn:country_code":"JO",
    "gn:dem":825,
    "gn:feature_class":"P",
    "gn:feature_code":"PPL",
    "gn:name":"Al Mi\u2018qar",
    "gn:population":0,
    "gn:timezone":"Asia/Amman",
    "iso:country":"JO",
    "name:ara_x_preferred":[
        "\u0627\u0644\u0645\u0639\u0642\u0631"
    ],
    "name:und_x_variant":[
        "Al Mi\u2018qar"
    ],
    "wof:name":"Al Mi`qar",
    "wof:placetype":"locality"
},
  "geometry": {"coordinates":[35.70625,31.68522],"type":"Point"}
}