{
  "type": "Feature",
  "properties": {
    "gn:admin1_code":"18",
    "gn:asciiname":"Juffayn",
    "gn:country_code":"JO",
    "gn:dem":312,
    "gn:feature_class":"P",
    "gn:feature_code":"PPL",
    "gn:name":"Juffayn",
    "gn:population":0,
    "gn:timezone":"Asia/Amman",
    "iso:country":"JO",
    "name:ara_x_preferred":[
        "\u062c\u0641\u064a\u0646"
    ],
    "name:und_x_variant":[
        "Jiff\u012bn",
        "Juffein",
        "Juffayn"
    ],
    "wof:name":"Juffayn",
    "wof:placetype":"locality"
},
  "geometry": {"coordinates":[35.65382,32.48895],"type":"Point"}
}