{
  "type": "Feature",
  "properties": {
    "gn:admin1_code":"19",
    "gn:asciiname":"Al Farsh",
    "gn:country_code":"JO",
    "gn:dem":1388,
    "gn:feature_class":"P",
    "gn:feature_code":"PPLL",
    "gn:name":"Al Farsh",
    "gn:population":0,
    "gn:timezone":"Asia/Amman",
    "iso:country":"JO",
    "name:ara_x_preferred":[
        "\u0627\u0644\u0641\u0631\u0634"
    ],
    "wof:name":"Al Farsh",
    "wof:placetype":"locality"
},
  "geometry": {"coordinates":[35.63301,29.86416],"type":"Point"}
}