{
  "type": "Feature",
  "properties": {
    "iso:country":"JO",
    "qs:gn_pop":0,
    "qs:name":"Shoubak Agriculture Community College",
    "qs:name_adm0":"\u0627\u0644\u0623\u0631\u062f\u0646",
    "qs:name_adm1":"\u0645\u0639\u0627\u0646",
    "qs:photos":55,
    "qs:photos_1k":11,
    "qs:photos_9k":1,
    "qs:photos_9r":2,
    "qs:photos_all":55,
    "qs:photos_sr":2,
    "qs:placetype":"Town",
    "qs:pop_sr":"0",
    "qs:woe_adm0":23424860,
    "wof:name":"Shoubak Agriculture Community College",
    "wof:placetype":"locality"
},
  "geometry": {"coordinates":[35.551053,30.53259],"type":"Point"}
}