{
  "type": "Feature",
  "properties": {
    "gn:admin1_code":"19",
    "gn:asciiname":"Adhruh",
    "gn:country_code":"JO",
    "gn:dem":1299,
    "gn:feature_class":"P",
    "gn:feature_code":"PPLA3",
    "gn:name":"Adhru\u1e29",
    "gn:population":0,
    "gn:timezone":"Asia/Amman",
    "iso:country":"JO",
    "name:ara_x_preferred":[
        "\u0623\u0630\u0631\u062d"
    ],
    "name:ara_x_variant":[
        "Adhru\u1e29"
    ],
    "name:und_x_variant":[
        "A\u1e11ru\u1e29",
        "Udhru\u1e29"
    ],
    "wof:name":"Adhruh",
    "wof:placetype":"locality"
},
  "geometry": {"coordinates":[35.59659,30.3307],"type":"Point"}
}