{
  "type": "Feature",
  "properties": {
    "gn:admin1_code":"02",
    "gn:asciiname":"Salhub",
    "gn:country_code":"JO",
    "gn:dem":783,
    "gn:feature_class":"P",
    "gn:feature_code":"PPL",
    "gn:name":"Sal\u1e29\u016bb",
    "gn:population":0,
    "gn:timezone":"Asia/Amman",
    "iso:country":"JO",
    "name:ara_x_preferred":[
        "\u0633\u0644\u062d\u0648\u0628"
    ],
    "name:und_x_variant":[
        "Sal\u1e29\u016bb"
    ],
    "wof:name":"Salhub",
    "wof:placetype":"locality"
},
  "geometry": {"coordinates":[35.86115,32.1252],"type":"Point"}
}