{
  "type": "Feature",
  "properties": {
    "gn:admin1_code":"15",
    "gn:asciiname":"`Ayn Bani Hasan",
    "gn:country_code":"JO",
    "gn:dem":723,
    "gn:feature_class":"P",
    "gn:feature_code":"PPL",
    "gn:name":"\u2018Ayn Ban\u012b \u1e28asan",
    "gn:population":0,
    "gn:timezone":"Asia/Amman",
    "iso:country":"JO",
    "name:ara_x_preferred":[
        "\u0639\u064a\u0646 \u0628\u0646\u064a \u062d\u0633\u0646"
    ],
    "name:ara_x_variant":[
        "\u062e\u0631\u0628\u0629 \u0639\u064a\u0646"
    ],
    "name:und_x_variant":[
        "Kh\u2018ain",
        "Khirbat \u2018Ain",
        "Khirbat \u2018Ayn",
        "\u2018Ayn Ban\u012b \u1e28asan"
    ],
    "wof:name":"`Ayn Bani Hasan",
    "wof:placetype":"locality"
},
  "geometry": {"coordinates":[36.05626,32.26969],"type":"Point"}
}