{
  "type": "Feature",
  "properties": {
    "gn:admin1_code":"19",
    "gn:asciiname":"Bada",
    "gn:country_code":"JO",
    "gn:dem":876,
    "gn:feature_class":"P",
    "gn:feature_code":"PPLL",
    "gn:name":"Bad\u0101",
    "gn:population":0,
    "gn:timezone":"Asia/Amman",
    "iso:country":"JO",
    "name:ara_x_preferred":[
        "\u0628\u062f\u0627"
    ],
    "name:und_x_variant":[
        "Bad\u0101"
    ],
    "wof:name":"Bada",
    "wof:placetype":"locality"
},
  "geometry": {"coordinates":[35.6052,30.60004],"type":"Point"}
}