{
  "type": "Feature",
  "properties": {
    "gn:admin1_code":"15",
    "gn:asciiname":"Subhiyah",
    "gn:country_code":"JO",
    "gn:dem":813,
    "gn:feature_class":"P",
    "gn:feature_code":"PPL",
    "gn:name":"\u015eub\u1e29\u012byah",
    "gn:population":0,
    "gn:timezone":"Asia/Amman",
    "iso:country":"JO",
    "name:ara_x_preferred":[
        "\u0635\u0628\u062d\u064a\u0629"
    ],
    "name:und_x_variant":[
        "Subh\u012bya",
        "\u015eub\u1e29\u012byah"
    ],
    "wof:name":"Subhiyah",
    "wof:placetype":"locality"
},
  "geometry": {"coordinates":[36.48495,32.34118],"type":"Point"}
}