{
  "type": "Feature",
  "properties": {
    "gn:admin1_code":"17",
    "gn:asciiname":"As Sahharah",
    "gn:country_code":"JO",
    "gn:dem":423,
    "gn:feature_class":"P",
    "gn:feature_code":"PPL",
    "gn:name":"As Sa\u1e29\u1e29\u0101rah",
    "gn:population":0,
    "gn:timezone":"Asia/Amman",
    "iso:country":"JO",
    "name:ara_x_preferred":[
        "\u0627\u0644\u0633\u062d\u0627\u0631\u0629"
    ],
    "name:und_x_variant":[
        "As Sa\u1e29\u1e29\u0101rah"
    ],
    "wof:name":"As Sahharah",
    "wof:placetype":"locality"
},
  "geometry": {"coordinates":[35.96015999999999,32.1819],"type":"Point"}
}