{
  "type": "Feature",
  "properties": {
    "gn:admin1_code":"18",
    "gn:asciiname":"Barashta",
    "gn:country_code":"JO",
    "gn:dem":445,
    "gn:feature_class":"P",
    "gn:feature_code":"PPL",
    "gn:name":"Barasht\u0101",
    "gn:population":0,
    "gn:timezone":"Asia/Amman",
    "iso:country":"JO",
    "name:ara_x_preferred":[
        "\u0628\u0631\u0634\u062a\u0627"
    ],
    "name:und_x_variant":[
        "Barasht\u0101"
    ],
    "wof:name":"Barashta",
    "wof:placetype":"locality"
},
  "geometry": {"coordinates":[35.87686,32.67202],"type":"Point"}
}