{
  "type": "Feature",
  "properties": {
    "gn:admin1_code":"16",
    "gn:asciiname":"Ash Shufatah",
    "gn:cc2":"JO",
    "gn:country_code":"JO",
    "gn:dem":742,
    "gn:feature_class":"P",
    "gn:feature_code":"PPL",
    "gn:name":"Ash Shufatah",
    "gn:population":0,
    "gn:timezone":"Asia/Amman",
    "iso:country":"JO",
    "name:nno_x_preferred":[
        "Ash Shufatah"
    ],
    "name:sco_x_preferred":[
        "Ash Shufatah"
    ],
    "name:sqi_x_preferred":[
        "Ash Shufatah"
    ],
    "name:und_x_variant":[
        "Esh Shufata"
    ],
    "wof:name":"Ash Shufatah",
    "wof:placetype":"locality"
},
  "geometry": {"coordinates":[35.96667,31.78333],"type":"Point"}
}