{
  "type": "Feature",
  "properties": {
    "gn:admin1_code":"18",
    "gn:asciiname":"Ash Shunah ash Shamaliyah",
    "gn:country_code":"JO",
    "gn:dem":-196,
    "gn:feature_class":"P",
    "gn:feature_code":"PPLA2",
    "gn:name":"Ash Sh\u016bnah ash Sham\u0101l\u012byah",
    "gn:population":0,
    "gn:timezone":"Asia/Amman",
    "iso:country":"JO",
    "name:ara_x_preferred":[
        "\u0627\u0644\u0634\u0648\u0646\u0629 \u0627\u0644\u0634\u0645\u0627\u0644\u064a\u0629"
    ],
    "name:und_x_variant":[
        "Shuna esh Shamaliya",
        "Khirbat ash Sh\u016bnah",
        "Sh\u016bna",
        "Ash Sh\u016bnah",
        "Shuna Shamaliya",
        "Khirbat esh Sh\u016bma",
        "Khirbat esh Shuna",
        "Khirbat Sh\u016bna",
        "Ash Sh\u016bnah ash Sham\u0101l\u012byah"
    ],
    "wof:name":"Ash Shunah ash Shamaliyah",
    "wof:placetype":"locality"
},
  "geometry": {"coordinates":[35.61451,32.62023],"type":"Point"}
}