{
  "type": "Feature",
  "properties": {
    "gn:admin1_code":"19",
    "gn:asciiname":"Az Zubayriyah",
    "gn:country_code":"JO",
    "gn:dem":1391,
    "gn:feature_class":"P",
    "gn:feature_code":"PPL",
    "gn:name":"Az Zubayr\u012byah",
    "gn:population":0,
    "gn:timezone":"Asia/Amman",
    "iso:country":"JO",
    "name:ara_x_preferred":[
        "\u0627\u0644\u0632\u0628\u064a\u0631\u064a\u0629"
    ],
    "name:und_x_variant":[
        "Az Zubayr\u012byah"
    ],
    "wof:name":"Az Zubayriyah",
    "wof:placetype":"locality"
},
  "geometry": {"coordinates":[35.56099000000001,30.50524],"type":"Point"}
}