{
  "type": "Feature",
  "properties": {
    "gn:admin1_code":"15",
    "gn:asciiname":"Manshiyat al Qablan",
    "gn:country_code":"JO",
    "gn:dem":876,
    "gn:feature_class":"P",
    "gn:feature_code":"PPL",
    "gn:name":"Mansh\u012byat al Qabl\u0101n",
    "gn:population":0,
    "gn:timezone":"Asia/Amman",
    "iso:country":"JO",
    "name:ara_x_preferred":[
        "\u0645\u0646\u0634\u064a\u0629 \u0627\u0644\u0642\u0628\u0644\u0627\u0646"
    ],
    "name:und_x_variant":[
        "Kh\u0101nah",
        "Khirbat el Kh\u0101n",
        "Khirbat al Kh\u0101n",
        "Mansh\u012byat al Qabl\u0101n"
    ],
    "wof:name":"Manshiyat al Qablan",
    "wof:placetype":"locality"
},
  "geometry": {"coordinates":[36.54387,32.33130999999999],"type":"Point"}
}