{
  "type": "Feature",
  "properties": {
    "gn:admin1_code":"23",
    "gn:asciiname":"Halaq ash Shuqayq",
    "gn:country_code":"JO",
    "gn:dem":732,
    "gn:feature_class":"P",
    "gn:feature_code":"PPL",
    "gn:name":"\u1e28alaq ash Shuqayq",
    "gn:population":0,
    "gn:timezone":"Asia/Amman",
    "iso:country":"JO",
    "name:ara_x_preferred":[
        "\u062d\u064e\u0644\u064e\u0642 \u0627\u0644\u0634\u0642\u064a\u0642"
    ],
    "name:ara_x_variant":[
        "\u062d\u0644\u0642 \u0627\u0644\u0634\u0642\u064a\u0642"
    ],
    "name:und_x_variant":[
        "\u1e24alaq esh Shuqeiq",
        "\u1e24alq",
        "El \u1e24alq",
        "\u1e28alaq ash Shuqayq"
    ],
    "wof:name":"Halaq ash Shuqayq",
    "wof:placetype":"locality"
},
  "geometry": {"coordinates":[35.72389000000001,31.49417],"type":"Point"}
}