{
  "type": "Feature",
  "properties": {
    "gn:admin1_code":"12",
    "gn:asciiname":"Shayzam",
    "gn:country_code":"JO",
    "gn:dem":1156,
    "gn:feature_class":"P",
    "gn:feature_code":"PPL",
    "gn:name":"Shayz\u0327am",
    "gn:population":0,
    "gn:timezone":"Asia/Amman",
    "iso:country":"JO",
    "name:ara_x_preferred":[
        "\u0634\u064a\u0638\u0645"
    ],
    "name:und_x_variant":[
        "Shayz\u0327am"
    ],
    "wof:name":"Shayzam",
    "wof:placetype":"locality"
},
  "geometry": {"coordinates":[35.67909,30.86644],"type":"Point"}
}