{
  "type": "Feature",
  "properties": {
    "iso:country":"JO",
    "name:ara_x_preferred":[
        "\u0647\u0627\u0643\u0627\u0645\u0627"
    ],
    "name:ara_x_variant":[
        "\u062d\u0643\u0645\u0627"
    ],
    "name:cat_x_preferred":[
        "Hakama"
    ],
    "name:cat_x_variant":[
        "hakama"
    ],
    "name:dan_x_preferred":[
        "Hakama"
    ],
    "name:deu_x_preferred":[
        "Hakama"
    ],
    "name:ell_x_preferred":[
        "\u03a7\u03b1\u03ba\u03ac\u03bc\u03b1"
    ],
    "name:eng_x_preferred":[
        "hakama"
    ],
    "name:fin_x_preferred":[
        "Hakama"
    ],
    "name:fra_x_preferred":[
        "Hakama"
    ],
    "name:fra_x_variant":[
        "hakama"
    ],
    "name:heb_x_preferred":[
        "\u05d4\u05d0\u05e7\u05d0\u05de\u05d4"
    ],
    "name:hun_x_preferred":[
        "Hakama"
    ],
    "name:ind_x_preferred":[
        "Hakama"
    ],
    "name:ita_x_preferred":[
        "Hakama"
    ],
    "name:ita_x_variant":[
        "hakama"
    ],
    "name:jav_x_preferred":[
        "Hakama"
    ],
    "name:jpn_x_preferred":[
        "\u88b4"
    ],
    "name:kat_x_preferred":[
        "\u10f0\u10d0\u10d9\u10d0\u10db\u10d0"
    ],
    "name:kor_x_preferred":[
        "\ud558\uce74\ub9c8"
    ],
    "name:nld_x_preferred":[
        "Hakama"
    ],
    "name:pan_x_preferred":[
        "\u0a39\u0a3e\u0a15\u0a3e\u0a2e\u0a3e"
    ],
    "name:pol_x_preferred":[
        "Hakama"
    ],
    "name:por_x_preferred":[
        "Hakama"
    ],
    "name:por_x_variant":[
        "hakama"
    ],
    "name:rus_x_preferred":[
        "\u0425\u0430\u043a\u0430\u043c\u0430"
    ],
    "name:spa_x_preferred":[
        "Hakama"
    ],
    "name:srp_x_preferred":[
        "\u0425\u0430\u043a\u0430\u043c\u0430"
    ],
    "name:swe_x_preferred":[
        "Hakama"
    ],
    "name:tur_x_preferred":[
        "Hakama"
    ],
    "name:ukr_x_preferred":[
        "\u0425\u0430\u043a\u0430\u043c\u0430"
    ],
    "name:und_x_variant":[
        "\u1e28akamah"
    ],
    "name:vie_x_preferred":[
        "Hakama"
    ],
    "name:zho_x_preferred":[
        "\u88b4"
    ],
    "qs:gn_country":"JO",
    "qs:gn_fcode":"PPL",
    "qs:gn_pop":7075,
    "qs:name":"Hakama",
    "qs:name_adm0":"\u0627\u0644\u0623\u0631\u062f\u0646",
    "qs:name_adm1":"\u0625\u0631\u0628\u062f",
    "qs:photos":0,
    "qs:photos_1k":0,
    "qs:photos_9k":0,
    "qs:photos_9r":0,
    "qs:photos_all":0,
    "qs:photos_sr":0,
    "qs:placetype":"Town",
    "qs:pop_sr":"5",
    "qs:woe_adm0":23424860,
    "wd:wordcount":1619,
    "wof:name":"Hakama",
    "wof:placetype":"locality",
    "wof:population":7075
},
  "geometry": {"coordinates":[35.88411,32.59445],"type":"Point"}
}