{
  "type": "Feature",
  "properties": {
    "gn:admin1_code":"17",
    "gn:asciiname":"An Nasiriyah",
    "gn:country_code":"JO",
    "gn:dem":868,
    "gn:feature_class":"P",
    "gn:feature_code":"PPL",
    "gn:name":"An N\u0101\u015fir\u012byah",
    "gn:population":0,
    "gn:timezone":"Asia/Amman",
    "iso:country":"JO",
    "name:ara_x_preferred":[
        "\u0627\u0644\u0646\u0627\u0635\u0631\u064a\u0629"
    ],
    "name:und_x_variant":[
        "An N\u0101\u015fir\u012byah"
    ],
    "wof:name":"An Nasiriyah",
    "wof:placetype":"locality"
},
  "geometry": {"coordinates":[35.89523,32.12377],"type":"Point"}
}