{
  "type": "Feature",
  "properties": {
    "gn:admin1_code":"09",
    "gn:asciiname":"Fayfa",
    "gn:country_code":"JO",
    "gn:dem":-320,
    "gn:feature_class":"P",
    "gn:feature_code":"PPL",
    "gn:name":"Fayf\u0101",
    "gn:population":0,
    "gn:timezone":"Asia/Amman",
    "iso:country":"JO",
    "name:ara_x_preferred":[
        "\u0641\u064a\u0641\u0627"
    ],
    "name:und_x_variant":[
        "F\u012bfah",
        "Fifi",
        "Fayf\u0101\u2019",
        "Fayf\u0101",
        "F\u012bf\u0101"
    ],
    "wof:name":"Fayfa",
    "wof:placetype":"locality"
},
  "geometry": {"coordinates":[35.45136,30.93593],"type":"Point"}
}