{
  "type": "Feature",
  "properties": {
    "gn:admin1_code":"23",
    "gn:asciiname":"Al Mushrifah",
    "gn:country_code":"JO",
    "gn:dem":644,
    "gn:feature_class":"P",
    "gn:feature_code":"PPL",
    "gn:name":"Al Mushrifah",
    "gn:population":0,
    "gn:timezone":"Asia/Amman",
    "iso:country":"JO",
    "name:ara_x_preferred":[
        "\u0627\u0644\u0645\u0634\u0631\u0641\u0629"
    ],
    "wof:name":"Al Mushrifah",
    "wof:placetype":"locality"
},
  "geometry": {"coordinates":[35.77646,31.54633],"type":"Point"}
}