{
  "type": "Feature",
  "properties": {
    "gn:admin1_code":"09",
    "gn:asciiname":"Muhayy",
    "gn:country_code":"JO",
    "gn:dem":1009,
    "gn:feature_class":"P",
    "gn:feature_code":"PPL",
    "gn:name":"Mu\u1e29ayy",
    "gn:population":0,
    "gn:timezone":"Asia/Amman",
    "iso:country":"JO",
    "name:ara_x_preferred":[
        "\u0645\u062d\u064a"
    ],
    "name:und_x_variant":[
        "Ma\u1e29ayy",
        "Muhay",
        "Maheiy",
        "Mu\u1e25ai",
        "Mu\u1e29ayy"
    ],
    "wof:name":"Muhayy",
    "wof:placetype":"locality"
},
  "geometry": {"coordinates":[35.86264,30.99212],"type":"Point"}
}