{
  "type": "Feature",
  "properties": {
    "gn:admin1_code":"22",
    "gn:asciiname":"Khirbat as Suwayrat",
    "gn:country_code":"JO",
    "gn:dem":268,
    "gn:feature_class":"P",
    "gn:feature_code":"PPL",
    "gn:name":"Khirbat as Suwayr\u0101t",
    "gn:population":0,
    "gn:timezone":"Asia/Amman",
    "iso:country":"JO",
    "name:und_x_variant":[
        "Khirbat Suweir\u0101t",
        "Khirbat as Suwayr\u0101t"
    ],
    "wof:name":"Khirbat as Suwayrat",
    "wof:placetype":"locality"
},
  "geometry": {"coordinates":[35.87302000000001,32.21352],"type":"Point"}
}