{
  "type": "Feature",
  "properties": {
    "gn:admin1_code":"23",
    "gn:asciiname":"Umm Nattulah",
    "gn:country_code":"JO",
    "gn:dem":524,
    "gn:feature_class":"P",
    "gn:feature_code":"PPLL",
    "gn:name":"Umm Natt\u016blah",
    "gn:population":0,
    "gn:timezone":"Asia/Amman",
    "iso:country":"JO",
    "name:ara_x_preferred":[
        "\u0627\u0645 \u0646\u062a\u0648\u0644\u0629"
    ],
    "name:und_x_variant":[
        "Umm Natt\u016blah"
    ],
    "wof:name":"Umm Nattulah",
    "wof:placetype":"locality"
},
  "geometry": {"coordinates":[35.79722,31.56132],"type":"Point"}
}