{
  "type": "Feature",
  "properties": {
    "gn:admin1_code":"15",
    "gn:asciiname":"Sab` Asir",
    "gn:country_code":"JO",
    "gn:dem":790,
    "gn:feature_class":"P",
    "gn:feature_code":"PPL",
    "gn:name":"Sab\u2018 A\u015f\u012br",
    "gn:population":0,
    "gn:timezone":"Asia/Amman",
    "iso:country":"JO",
    "name:ara_x_preferred":[
        "\u0633\u0628\u0639 \u0627\u0635\u064a\u0631"
    ],
    "name:ara_x_variant":[
        "\u0643\u0648\u0645 \u0627\u0644\u0631\u0641"
    ],
    "name:und_x_variant":[
        "Sab\u2018 \u015eiyar",
        "Sab\u2018 A\u015f\u012br",
        "Sab\u2018 I\u015f\u015f\u012br",
        "Kawm ar Riff"
    ],
    "wof:name":"Sab` Asir",
    "wof:placetype":"locality"
},
  "geometry": {"coordinates":[36.46403,32.33845],"type":"Point"}
}