{
  "type": "Feature",
  "properties": {
    "iso:country":"JO",
    "name:unk_x_variant":[
        "Deir el Liyy\u0101\u1e6d"
    ],
    "qs:gn_country":"JO",
    "qs:gn_fcode":"PPL",
    "qs:gn_pop":0,
    "qs:name":"Dayr al Liyat",
    "qs:name_adm0":"\u0627\u0644\u0623\u0631\u062f\u0646",
    "qs:name_adm1":"\u062c\u0631\u0634",
    "qs:photos":104,
    "qs:photos_1k":21,
    "qs:photos_9k":1,
    "qs:photos_9r":3,
    "qs:photos_all":104,
    "qs:photos_sr":3,
    "qs:placetype":"Town",
    "qs:pop_sr":"0",
    "qs:woe_adm0":23424860,
    "wof:name":"Dayr al Liyat",
    "wof:placetype":"locality"
},
  "geometry": {"coordinates":[35.87535,32.29498],"type":"Point"}
}