{
  "type": "Feature",
  "properties": {
    "gn:admin1_code":"20",
    "gn:asciiname":"Ras al Aqra`",
    "gn:country_code":"JO",
    "gn:dem":816,
    "gn:feature_class":"P",
    "gn:feature_code":"PPL",
    "gn:name":"R\u0101s al Aqra\u2018",
    "gn:population":0,
    "gn:timezone":"Asia/Amman",
    "iso:country":"JO",
    "name:ara_x_preferred":[
        "\u0631\u0627\u0633 \u0627\u0644\u0627\u0642\u0631\u0639"
    ],
    "name:und_x_variant":[
        "R\u0101s al Aqra\u2018"
    ],
    "wof:name":"Ras al Aqra`",
    "wof:placetype":"locality"
},
  "geometry": {"coordinates":[35.72456,32.22888],"type":"Point"}
}