{
  "type": "Feature",
  "properties": {
    "gn:admin1_code":"18",
    "gn:asciiname":"Rehaba",
    "gn:country_code":"JO",
    "gn:dem":913,
    "gn:feature_class":"P",
    "gn:feature_code":"PPL",
    "gn:name":"Rehaba",
    "gn:population":0,
    "gn:timezone":"Asia/Amman",
    "iso:country":"JO",
    "name:ara_x_preferred":[
        "\u0625\u0631\u062d\u0627\u0628\u0627"
    ],
    "name:ara_x_variant":[
        "\u0631\u062d\u0627\u0628\u0627"
    ],
    "name:und_x_variant":[
        "Ar\u1e29\u0101b\u0101",
        "Rehaba",
        "Ri\u1e29\u0101b\u0101"
    ],
    "wof:name":"Rehaba",
    "wof:placetype":"locality"
},
  "geometry": {"coordinates":[35.78528,32.43247],"type":"Point"}
}