{
  "type": "Feature",
  "properties": {
    "gn:admin1_code":"02",
    "gn:asciiname":"Al Birah",
    "gn:country_code":"JO",
    "gn:dem":540,
    "gn:feature_class":"P",
    "gn:feature_code":"PPL",
    "gn:name":"Al B\u012brah",
    "gn:population":0,
    "gn:timezone":"Asia/Amman",
    "iso:country":"JO",
    "name:ara_x_preferred":[
        "\u0627\u0644\u0628\u064a\u0631\u0629"
    ],
    "name:und_x_variant":[
        "Khirbat el B\u012bra",
        "Khirbat al B\u012brah",
        "Al B\u012brah"
    ],
    "wof:name":"Al Birah",
    "wof:placetype":"locality"
},
  "geometry": {"coordinates":[35.68729000000001,31.98929],"type":"Point"}
}