{
  "type": "Feature",
  "properties": {
    "gn:admin1_code":"15",
    "gn:asciiname":"Al Khalidiyah ash Sharqiyah",
    "gn:country_code":"JO",
    "gn:dem":636,
    "gn:feature_class":"P",
    "gn:feature_code":"PPL",
    "gn:name":"Al Kh\u0101lid\u012byah ash Sharq\u012byah",
    "gn:population":0,
    "gn:timezone":"Asia/Amman",
    "iso:country":"JO",
    "name:ara_x_preferred":[
        "Al Qi\u1e29\u0101\u0163\u012b"
    ],
    "name:ara_x_variant":[
        "\u0627\u0644\u062e\u0627\u0644\u062f\u064a\u0629 \u0627\u0644\u0634\u0631\u0642\u064a\u0629"
    ],
    "name:und_x_variant":[
        "El Qih\u0101t\u012b",
        "Al Kh\u0101lid\u012byah ash Sharq\u012byah"
    ],
    "wof:name":"Al Khalidiyah ash Sharqiyah",
    "wof:placetype":"locality"
},
  "geometry": {"coordinates":[36.32799,32.18607],"type":"Point"}
}