{
  "type": "Feature",
  "properties": {
    "iso:country":"JO",
    "name:ara_x_preferred":[
        "\u0627\u0644\u0645\u0634\u0642\u0631"
    ],
    "name:dut_x_preferred":[
        "Al Mushaqqar"
    ],
    "name:eng_x_preferred":[
        "Al Mushaqqar"
    ],
    "name:fas_x_preferred":[
        "\u0645\u0634\u0642\u0631"
    ],
    "name:nno_x_preferred":[
        "Al Mushaqqar"
    ],
    "name:per_x_preferred":[
        "\u0627\u0644\u0645\u0634\u0642\u0631"
    ],
    "name:sco_x_preferred":[
        "Al Mushaqqar"
    ],
    "name:unk_x_variant":[
        "El Mushaqqer"
    ],
    "qs:gn_country":"JO",
    "qs:gn_fcode":"PPL",
    "qs:gn_pop":0,
    "qs:name":"Al Mushaqqar",
    "qs:name_adm0":"\u0627\u0644\u0623\u0631\u062f\u0646",
    "qs:name_adm1":"\u0639\u0645\u0627\u0646",
    "qs:photos":14,
    "qs:photos_1k":3,
    "qs:photos_9k":1,
    "qs:photos_9r":1,
    "qs:photos_all":14,
    "qs:photos_sr":1,
    "qs:placetype":"Town",
    "qs:pop_sr":"0",
    "qs:woe_adm0":23424860,
    "wd:wordcount":30,
    "wof:name":"Al Mushaqqar",
    "wof:placetype":"locality"
},
  "geometry": {"coordinates":[35.78614,31.7902],"type":"Point"}
}