{
  "type": "Feature",
  "properties": {
    "iso:country":"JO",
    "name:ara_x_preferred":[
        "\u0627\u0644\u0637\u064a\u0628\u0629"
    ],
    "name:und_x_variant":[
        "Taiyiba"
    ],
    "qs:gn_country":"JO",
    "qs:gn_fcode":"PPL",
    "qs:gn_pop":4265,
    "qs:name":"At Tayyibah",
    "qs:name_adm0":"\u0627\u0644\u0623\u0631\u062f\u0646",
    "qs:name_adm1":"\u0645\u0639\u0627\u0646",
    "qs:photos":75,
    "qs:photos_1k":15,
    "qs:photos_9k":1,
    "qs:photos_9r":2,
    "qs:photos_all":75,
    "qs:photos_sr":2,
    "qs:placetype":"Town",
    "qs:pop_sr":"4",
    "qs:woe_adm0":23424860,
    "wof:name":"At Tayyibah",
    "wof:placetype":"locality",
    "wof:population":4265
},
  "geometry": {"coordinates":[35.45997,30.25661],"type":"Point"}
}