{
  "type": "Feature",
  "properties": {
    "gn:admin1_code":"16",
    "gn:asciiname":"Muzayyir `Alya",
    "gn:country_code":"JO",
    "gn:dem":689,
    "gn:feature_class":"P",
    "gn:feature_code":"PPL",
    "gn:name":"Muzayyir \u2018Aly\u0101",
    "gn:population":0,
    "gn:timezone":"Asia/Amman",
    "iso:country":"JO",
    "name:ara_x_preferred":[
        "\u0645\u0632\u064a\u0631 \u0639\u0644\u064a\u0627"
    ],
    "name:und_x_variant":[
        "Mezyer \u2018Alya",
        "Muzaiyar \u2018Aly\u0101",
        "Muzeir \u2018Aly\u0101",
        "Muzayyir \u2018Aly\u0101"
    ],
    "wof:name":"Muzayyir `Alya",
    "wof:placetype":"locality"
},
  "geometry": {"coordinates":[35.86952,31.56136],"type":"Point"}
}