{
  "type": "Feature",
  "properties": {
    "gn:admin1_code":"18",
    "gn:asciiname":"Al Qasabat",
    "gn:country_code":"JO",
    "gn:dem":161,
    "gn:feature_class":"P",
    "gn:feature_code":"PPL",
    "gn:name":"Al Qa\u015fab\u0101t",
    "gn:population":0,
    "gn:timezone":"Asia/Amman",
    "iso:country":"JO",
    "name:ara_x_preferred":[
        "\u0627\u0644\u0642\u0635\u0628\u0627\u062a"
    ],
    "name:und_x_variant":[
        "Al Qa\u015fab\u0101t"
    ],
    "wof:name":"Al Qasabat",
    "wof:placetype":"locality"
},
  "geometry": {"coordinates":[35.63749,32.46347],"type":"Point"}
}