{
  "type": "Feature",
  "properties": {
    "gn:admin1_code":"09",
    "gn:asciiname":"Khirbat Majdalayn",
    "gn:country_code":"JO",
    "gn:dem":907,
    "gn:feature_class":"P",
    "gn:feature_code":"PPL",
    "gn:name":"Khirbat Majdalayn",
    "gn:population":0,
    "gn:timezone":"Asia/Amman",
    "iso:country":"JO",
    "name:und_x_variant":[
        "Majdalin",
        "Khirbat Majdalein",
        "Majd\u016bl\u012bn",
        "Majdolin",
        "Khirbat Majdalayn"
    ],
    "wof:name":"Khirbat Majdalayn",
    "wof:placetype":"locality"
},
  "geometry": {"coordinates":[35.71635999999999,31.33449],"type":"Point"}
}