{
  "type": "Feature",
  "properties": {
    "iso:country":"JO",
    "name:ara_x_preferred":[
        "\u0627\u0631\u064a\u062d\u0627"
    ],
    "name:eng_x_preferred":[
        "Ariha"
    ],
    "qs:gn_pop":0,
    "qs:name":"\u0627\u0631\u064a\u062d\u0627",
    "qs:name_adm0":"\u0627\u0644\u0623\u0631\u062f\u0646",
    "qs:name_adm1":"\u0627\u0644\u0643\u0631\u0643",
    "qs:photos":136,
    "qs:photos_1k":28,
    "qs:photos_9k":1,
    "qs:photos_9r":3,
    "qs:photos_all":136,
    "qs:photos_sr":3,
    "qs:placetype":"Town",
    "qs:pop_sr":"0",
    "qs:woe_adm0":23424860,
    "wof:name":"Ariha",
    "wof:placetype":"locality"
},
  "geometry": {"coordinates":[35.803667,31.441893],"type":"Point"}
}