{
  "type": "Feature",
  "properties": {
    "gn:admin1_code":"15",
    "gn:asciiname":"Bal`ama",
    "gn:country_code":"JO",
    "gn:dem":673,
    "gn:feature_class":"P",
    "gn:feature_code":"PPLA3",
    "gn:name":"Bal\u2018am\u0101",
    "gn:population":0,
    "gn:timezone":"Asia/Amman",
    "iso:country":"JO",
    "name:ara_x_preferred":[
        "\u0628\u0644\u0639\u0645\u0627"
    ],
    "name:und_x_variant":[
        "Bal\u2018amah",
        "Bel\u2018ama",
        "Bal\u2018am\u0101"
    ],
    "wof:name":"Bal`ama",
    "wof:placetype":"locality"
},
  "geometry": {"coordinates":[36.08811,32.23649],"type":"Point"}
}