{
  "type": "Feature",
  "properties": {
    "gn:admin1_code":"18",
    "gn:asciiname":"Khirbat ash Shaykh Husayn",
    "gn:country_code":"JO",
    "gn:dem":-196,
    "gn:feature_class":"P",
    "gn:feature_code":"PPL",
    "gn:name":"Khirbat ash Shaykh \u1e28usayn",
    "gn:population":0,
    "gn:timezone":"Asia/Amman",
    "iso:country":"JO",
    "name:ara_x_preferred":[
        "\u062e\u0631\u0628\u0629 \u0627\u0644\u0634\u064a\u062e \u062d\u0633\u064a\u0646"
    ],
    "name:und_x_variant":[
        "Khirbat esh Sheikh Husein",
        "Khirbat Sheikh Husein",
        "Khirbat ash Shaykh \u1e28usayn"
    ],
    "wof:name":"Khirbat ash Shaykh Husayn",
    "wof:placetype":"locality"
},
  "geometry": {"coordinates":[35.60908,32.61151],"type":"Point"}
}