{
  "type": "Feature",
  "properties": {
    "gn:admin1_code":"15",
    "gn:asciiname":"Mahattat al Jufur",
    "gn:country_code":"JO",
    "gn:dem":689,
    "gn:feature_class":"P",
    "gn:feature_code":"PPL",
    "gn:name":"Ma\u1e29a\u0163\u0163at al Juf\u016br",
    "gn:population":0,
    "gn:timezone":"Asia/Amman",
    "iso:country":"JO",
    "name:und_x_variant":[
        "Ma\u1e25a\u1e6d\u1e6dat el J\u016bfur",
        "Ma\u1e29a\u0163\u0163at al Juf\u016br"
    ],
    "wof:name":"Mahattat al Jufur",
    "wof:placetype":"locality"
},
  "geometry": {"coordinates":[38.20076,32.50414],"type":"Point"}
}