{
  "type": "Feature",
  "properties": {
    "iso:country":"JO",
    "name:ara_x_preferred":[
        "\u0634\u064a\u0647\u0627\u0646"
    ],
    "name:cat_x_preferred":[
        "Shihan"
    ],
    "name:dan_x_preferred":[
        "Shihan"
    ],
    "name:deu_x_preferred":[
        "Shihan"
    ],
    "name:fas_x_preferred":[
        "\u0634\u06cc\u0647\u0627\u0646"
    ],
    "name:fin_x_preferred":[
        "Shihan"
    ],
    "name:fra_x_preferred":[
        "Shihan"
    ],
    "name:ita_x_preferred":[
        "Shihan"
    ],
    "name:jpn_x_preferred":[
        "\u5e2b\u7bc4"
    ],
    "name:pol_x_preferred":[
        "Shihan"
    ],
    "name:por_x_preferred":[
        "Shihan"
    ],
    "name:rus_x_preferred":[
        "\u0421\u0438\u0445\u0430\u043d"
    ],
    "name:spa_x_preferred":[
        "Shihan"
    ],
    "name:srp_x_preferred":[
        "\u0428\u0438\u0445\u0430\u043d"
    ],
    "name:swe_x_preferred":[
        "Shihan"
    ],
    "qs:gn_pop":0,
    "qs:name":"Shihan",
    "qs:name_adm0":"\u0627\u0644\u0623\u0631\u062f\u0646",
    "qs:name_adm1":"\u0627\u0644\u0643\u0631\u0643",
    "qs:photos":24,
    "qs:photos_1k":5,
    "qs:photos_9k":1,
    "qs:photos_9r":1,
    "qs:photos_all":24,
    "qs:photos_sr":1,
    "qs:placetype":"Town",
    "qs:pop_sr":"0",
    "qs:woe_adm0":23424860,
    "wd:wordcount":227,
    "wof:name":"Shihan",
    "wof:placetype":"locality"
},
  "geometry": {"coordinates":[35.763244,31.351291],"type":"Point"}
}