{
  "type": "Feature",
  "properties": {
    "gn:admin1_code":"17",
    "gn:asciiname":"Khirbat ar Rusayfah",
    "gn:country_code":"JO",
    "gn:dem":679,
    "gn:feature_class":"P",
    "gn:feature_code":"PPL",
    "gn:name":"Khirbat ar Ru\u015fayfah",
    "gn:population":0,
    "gn:timezone":"Asia/Amman",
    "iso:country":"JO",
    "name:und_x_variant":[
        "Khirbat er Ruseifa",
        "Khirbat ar Ru\u015fayfah"
    ],
    "wof:name":"Khirbat ar Rusayfah",
    "wof:placetype":"locality"
},
  "geometry": {"coordinates":[36.01462,32.02176],"type":"Point"}
}