{
  "type": "Feature",
  "properties": {
    "gn:admin1_code":"18",
    "gn:asciiname":"Zabdah al Wasatiyah",
    "gn:country_code":"JO",
    "gn:dem":295,
    "gn:feature_class":"P",
    "gn:feature_code":"PPL",
    "gn:name":"Zabdah al Wasa\u0163\u012byah",
    "gn:population":0,
    "gn:timezone":"Asia/Amman",
    "iso:country":"JO",
    "name:ara_x_preferred":[
        "\u0632\u0628\u062f\u0629 \u0627\u0644\u0648\u0633\u0637\u064a\u0629"
    ],
    "name:ara_x_variant":[
        "\u0632\u0628\u062f\u0629"
    ],
    "name:und_x_variant":[
        "Zabda",
        "Zabdah",
        "Zabdah al Wasa\u0163\u012byah"
    ],
    "wof:name":"Zabdah al Wasatiyah",
    "wof:placetype":"locality"
},
  "geometry": {"coordinates":[35.66823,32.57136],"type":"Point"}
}