{
  "type": "Feature",
  "properties": {
    "gn:country":"JO",
    "gn:fcode":"PPL",
    "gn:pop":8926,
    "iso:country":"JO",
    "name:ara_x_preferred":[
        "\u0635\u0645\u0627"
    ],
    "name:eng_x_preferred":[
        "samma"
    ],
    "name:unk_x_variant":[
        "Sammeh"
    ],
    "qs:name":"\u015eamm\u0101",
    "qs:photos_9r":0,
    "qs:photos_sr":0,
    "qs:pop_sr":"5",
    "wof:name":"\u015eamm\u0101",
    "wof:placetype":"locality",
    "wof:population":8926
},
  "geometry": {"coordinates":[35.69025,32.57103],"type":"Point"}
}