{
  "type": "Feature",
  "properties": {
    "gn:admin1_code":"18",
    "gn:asciiname":"At Tabriyat",
    "gn:country_code":"JO",
    "gn:dem":440,
    "gn:feature_class":"P",
    "gn:feature_code":"PPL",
    "gn:name":"A\u0163 \u0162abriy\u0101t",
    "gn:population":0,
    "gn:timezone":"Asia/Amman",
    "iso:country":"JO",
    "name:ara_x_preferred":[
        "\u0627\u0644\u0637\u0628\u0631\u064a\u0627\u062a"
    ],
    "name:und_x_variant":[
        "A\u0163 \u0162abriy\u0101t"
    ],
    "wof:name":"At Tabriyat",
    "wof:placetype":"locality"
},
  "geometry": {"coordinates":[35.96001,32.68014],"type":"Point"}
}