{
  "type": "Feature",
  "properties": {
    "gn:admin1_code":"22",
    "gn:asciiname":"Khirbat Qirfill",
    "gn:country_code":"JO",
    "gn:dem":587,
    "gn:feature_class":"P",
    "gn:feature_code":"PPL",
    "gn:name":"Khirbat Qirfill",
    "gn:population":0,
    "gn:timezone":"Asia/Amman",
    "iso:country":"JO",
    "name:und_x_variant":[
        "Khirbat Pirmill",
        "Khirbat Qirfill"
    ],
    "wof:name":"Khirbat Qirfill",
    "wof:placetype":"locality"
},
  "geometry": {"coordinates":[35.90635,32.2639],"type":"Point"}
}