{
  "type": "Feature",
  "properties": {
    "gn:country":"JO",
    "gn:fcode":"BLDG",
    "gn:pop":5000,
    "iso:country":"JO",
    "qs:name":"Jordan Gate",
    "qs:photos_9r":0,
    "qs:photos_sr":0,
    "qs:pop_sr":"4",
    "wd:wordcount":475,
    "wof:name":"Jordan Gate",
    "wof:placetype":"locality",
    "wof:population":5000
},
  "geometry": {"coordinates":[35.86893,31.9634],"type":"Point"}
}